[
    {
        "ano": 2021,
        "mes": 11,
        "tipoDespesa": "MANUTENÇÃO DE ESCRITÓRIO DE APOIO À ATIVIDADE PARLAMENTAR",
        "codDocumento": 7294261,
        "tipoDocumento": "Recibos/Outros",
        "codTipoDocumento": 1,
        "dataDocumento": "2021-11-25",
        "numDocumento": "0312",
        "valorDocumento": 3500.0,
        "urlDocumento": "https://www.camara.leg.br/cota-parlamentar/documentos/publ/3034/2021/7294261.pdf",
        "nomeFornecedor": "ERIKA FERREIRA LOO LI",
        "cnpjCpfFornecedor": "34180303272",
        "valorLiquido": 3500.0,
        "valorGlosa": 0.0,
        "numRessarcimento": "",
        "codLote": 1811298,
        "parcela": 0
    },
    {
        "ano": 2021,
        "mes": 12,
        "tipoDespesa": "MANUTENÇÃO DE ESCRITÓRIO DE APOIO À ATIVIDADE PARLAMENTAR",
        "codDocumento": 7310839,
        "tipoDocumento": "Recibos/Outros",
        "codTipoDocumento": 1,
        "dataDocumento": "2021-12-27",
        "numDocumento": "04/12",
        "valorDocumento": 3500.0,
        "urlDocumento": "https://www.camara.leg.br/cota-parlamentar/documentos/publ/3034/2021/7310839.pdf",
        "nomeFornecedor": "ERIKA FERREIRA LOO LI",
        "cnpjCpfFornecedor": "34180303272",
        "valorLiquido": 3500.0,
        "valorGlosa": 0.0,
        "numRessarcimento": "",
        "codLote": 1819006,
        "parcela": 0
    },
    {
        "ano": 2021,
        "mes": 11,
        "tipoDespesa": "MANUTENÇÃO DE ESCRITÓRIO DE APOIO À ATIVIDADE PARLAMENTAR",
        "codDocumento": 7292576,
        "tipoDocumento": "Nota Fiscal Eletrônica",
        "codTipoDocumento": 4,
        "dataDocumento": "2021-11-19",
        "numDocumento": "467",
        "valorDocumento": 3797.0,
        "urlDocumento": "http://camara.leg.br/cota-parlamentar/nota-fiscal-eletronica?ideDocumentoFiscal=7292576",
        "nomeFornecedor": "R S IGLESIAS",
        "cnpjCpfFornecedor": "01067007000193",
        "valorLiquido": 3527.0,
        "valorGlosa": 270.0,
        "numRessarcimento": "",
        "codLote": 1810581,
        "parcela": 0
    },
    {
        "ano": 2021,
        "mes": 12,
        "tipoDespesa": "COMBUSTÍVEIS E LUBRIFICANTES.",
        "codDocumento": 7298491,
        "tipoDocumento": "Nota Fiscal Eletrônica",
        "codTipoDocumento": 4,
        "dataDocumento": "2021-12-02",
        "numDocumento": "2647",
        "valorDocumento": 2394.07,
        "urlDocumento": "http://camara.leg.br/cota-parlamentar/nota-fiscal-eletronica?ideDocumentoFiscal=7298491",
        "nomeFornecedor": "R  R EMPREENDIMENTOS EIRELI EPP",
        "cnpjCpfFornecedor": "10929612000117",
        "valorLiquido": 2394.07,
        "valorGlosa": 0.0,
        "numRessarcimento": "",
        "codLote": 1813264,
        "parcela": 0
    },
    {
        "ano": 2021,
        "mes": 12,
        "tipoDespesa": "COMBUSTÍVEIS E LUBRIFICANTES.",
        "codDocumento": 7311142,
        "tipoDocumento": "Nota Fiscal Eletrônica",
        "codTipoDocumento": 4,
        "dataDocumento": "2021-12-27",
        "numDocumento": "2661",
        "valorDocumento": 1011.43,
        "urlDocumento": "http://camara.leg.br/cota-parlamentar/nota-fiscal-eletronica?ideDocumentoFiscal=7311142",
        "nomeFornecedor": "R  R EMPREENDIMENTOS EIRELI EPP",
        "cnpjCpfFornecedor": "10929612000117",
        "valorLiquido": 1011.43,
        "valorGlosa": 0.0,
        "numRessarcimento": "",
        "codLote": 1819157,
        "parcela": 0
    },
    {
        "ano": 2021,
        "mes": 12,
        "tipoDespesa": "COMBUSTÍVEIS E LUBRIFICANTES.",
        "codDocumento": 7305452,
        "tipoDocumento": "Nota Fiscal Eletrônica",
        "codTipoDocumento": 4,
        "dataDocumento": "2021-12-02",
        "numDocumento": "980",
        "valorDocumento": 2563.86,
        "urlDocumento": "http://camara.leg.br/cota-parlamentar/nota-fiscal-eletronica?ideDocumentoFiscal=7305452",
        "nomeFornecedor": "RR EMPREENDIMENTOS EIRELLIEPP",
        "cnpjCpfFornecedor": "10929612000460",
        "valorLiquido": 2563.86,
        "valorGlosa": 0.0,
        "numRessarcimento": "",
        "codLote": 1816525,
        "parcela": 0
    },
    {
        "ano": 2021,
        "mes": 12,
        "tipoDespesa": "DIVULGAÇÃO DA ATIVIDADE PARLAMENTAR.",
        "codDocumento": 7302505,
        "tipoDocumento": "Nota Fiscal",
        "codTipoDocumento": 0,
        "dataDocumento": "2021-12-09",
        "numDocumento": "2021000025",
        "valorDocumento": 1500.0,
        "urlDocumento": "https://www.camara.leg.br/cota-parlamentar/documentos/publ/3034/2021/7302505.pdf",
        "nomeFornecedor": "ASSOCIACAO COMUNITARIA DE COMUNICACAO ONDA LIVRE",
        "cnpjCpfFornecedor": "04788024000108",
        "valorLiquido": 1500.0,
        "valorGlosa": 0.0,
        "numRessarcimento": "",
        "codLote": 1815251,
        "parcela": 0
    },
    {
        "ano": 2021,
        "mes": 11,
        "tipoDespesa": "DIVULGAÇÃO DA ATIVIDADE PARLAMENTAR.",
        "codDocumento": 7295286,
        "tipoDocumento": "Nota Fiscal",
        "codTipoDocumento": 0,
        "dataDocumento": "2021-11-25",
        "numDocumento": "281",
        "valorDocumento": 2000.0,
        "urlDocumento": "https://www.camara.leg.br/cota-parlamentar/documentos/publ/3034/2021/7295286.pdf",
        "nomeFornecedor": "CLAUDIO GOMES DA SILVA ME",
        "cnpjCpfFornecedor": "20357070000109",
        "valorLiquido": 2000.0,
        "valorGlosa": 0.0,
        "numRessarcimento": "",
        "codLote": 1811741,
        "parcela": 0
    },
    {
        "ano": 2021,
        "mes": 12,
        "tipoDespesa": "DIVULGAÇÃO DA ATIVIDADE PARLAMENTAR.",
        "codDocumento": 7321865,
        "tipoDocumento": "Nota Fiscal Eletrônica",
        "codTipoDocumento": 4,
        "dataDocumento": "2021-12-22",
        "numDocumento": "289",
        "valorDocumento": 2000.0,
        "urlDocumento": "http://camara.leg.br/cota-parlamentar/nota-fiscal-eletronica?ideDocumentoFiscal=7321865",
        "nomeFornecedor": "CLAUDIO GOMES DA SILVA ME",
        "cnpjCpfFornecedor": "20357070000109",
        "valorLiquido": 2000.0,
        "valorGlosa": 0.0,
        "numRessarcimento": "",
        "codLote": 1824363,
        "parcela": 0
    },
    {
        "ano": 2021,
        "mes": 11,
        "tipoDespesa": "DIVULGAÇÃO DA ATIVIDADE PARLAMENTAR.",
        "codDocumento": 7298277,
        "tipoDocumento": "Nota Fiscal",
        "codTipoDocumento": 0,
        "dataDocumento": "2021-12-02",
        "numDocumento": "118",
        "valorDocumento": 12800.0,
        "urlDocumento": "https://www.camara.leg.br/cota-parlamentar/documentos/publ/3034/2021/7298277.pdf",
        "nomeFornecedor": "K. D. DA SILVA GOES",
        "cnpjCpfFornecedor": "32756633000110",
        "valorLiquido": 12800.0,
        "valorGlosa": 0.0,
        "numRessarcimento": "",
        "codLote": 1813185,
        "parcela": 0
    },
    {
        "ano": 2021,
        "mes": 12,
        "tipoDespesa": "DIVULGAÇÃO DA ATIVIDADE PARLAMENTAR.",
        "codDocumento": 7309930,
        "tipoDocumento": "Nota Fiscal",
        "codTipoDocumento": 0,
        "dataDocumento": "2021-12-21",
        "numDocumento": "202100000000120",
        "valorDocumento": 12800.0,
        "urlDocumento": "https://www.camara.leg.br/cota-parlamentar/documentos/publ/3034/2021/7309930.pdf",
        "nomeFornecedor": "K.D DA SILVA GOES",
        "cnpjCpfFornecedor": "32756633000110",
        "valorLiquido": 12800.0,
        "valorGlosa": 0.0,
        "numRessarcimento": "",
        "codLote": 1818564,
        "parcela": 0
    },
    {
        "ano": 2021,
        "mes": 10,
        "tipoDespesa": "TELEFONIA",
        "codDocumento": 0,
        "tipoDocumento": "Nota Fiscal",
        "codTipoDocumento": 0,
        "dataDocumento": "2021-12-02",
        "numDocumento": "7300957",
        "valorDocumento": 116.43,
        "urlDocumento": null,
        "nomeFornecedor": "CELULAR FUNCIONAL",
        "cnpjCpfFornecedor": "00000000000001",
        "valorLiquido": 116.43,
        "valorGlosa": 0.0,
        "numRessarcimento": "0",
        "codLote": 0,
        "parcela": 0
    },
    {
        "ano": 2021,
        "mes": 11,
        "tipoDespesa": "TELEFONIA",
        "codDocumento": 0,
        "tipoDocumento": "Nota Fiscal",
        "codTipoDocumento": 0,
        "dataDocumento": "2022-01-06",
        "numDocumento": "7314919",
        "valorDocumento": 116.43,
        "urlDocumento": null,
        "nomeFornecedor": "CELULAR FUNCIONAL",
        "cnpjCpfFornecedor": "00000000000001",
        "valorLiquido": 116.43,
        "valorGlosa": 0.0,
        "numRessarcimento": "0",
        "codLote": 0,
        "parcela": 0
    },
    {
        "ano": 2021,
        "mes": 12,
        "tipoDespesa": "TELEFONIA",
        "codDocumento": 0,
        "tipoDocumento": "Nota Fiscal",
        "codTipoDocumento": 0,
        "dataDocumento": "2022-02-09",
        "numDocumento": "7349372",
        "valorDocumento": 116.43,
        "urlDocumento": null,
        "nomeFornecedor": "CELULAR FUNCIONAL",
        "cnpjCpfFornecedor": "00000000000001",
        "valorLiquido": 116.43,
        "valorGlosa": 0.0,
        "numRessarcimento": "0",
        "codLote": 0,
        "parcela": 0
    },
    {
        "ano": 2021,
        "mes": 12,
        "tipoDespesa": "TELEFONIA",
        "codDocumento": 7311556,
        "tipoDocumento": "Nota Fiscal",
        "codTipoDocumento": 0,
        "dataDocumento": "2021-12-18",
        "numDocumento": "0001693343",
        "valorDocumento": 474.43,
        "urlDocumento": null,
        "nomeFornecedor": "Claro NXT Telecomunicações S.A",
        "cnpjCpfFornecedor": "66970229001805",
        "valorLiquido": 170.81,
        "valorGlosa": 303.62,
        "numRessarcimento": "",
        "codLote": 1819342,
        "parcela": 0
    },
    {
        "ano": 2021,
        "mes": 11,
        "tipoDespesa": "TELEFONIA",
        "codDocumento": 7303720,
        "tipoDocumento": "Nota Fiscal",
        "codTipoDocumento": 0,
        "dataDocumento": "2021-12-01",
        "numDocumento": "00001120040982",
        "valorDocumento": 249.99,
        "urlDocumento": null,
        "nomeFornecedor": "Telefônica Brasil S.A. Vivo",
        "cnpjCpfFornecedor": "02558157000162",
        "valorLiquido": 249.99,
        "valorGlosa": 0.0,
        "numRessarcimento": "",
        "codLote": 1815827,
        "parcela": 0
    },
    {
        "ano": 2021,
        "mes": 12,
        "tipoDespesa": "TELEFONIA",
        "codDocumento": 7313578,
        "tipoDocumento": "Nota Fiscal",
        "codTipoDocumento": 0,
        "dataDocumento": "2022-01-01",
        "numDocumento": "1266951",
        "valorDocumento": 255.22,
        "urlDocumento": null,
        "nomeFornecedor": "Telefônica Brasil S.A. VIVO",
        "cnpjCpfFornecedor": "02558157000162",
        "valorLiquido": 249.99,
        "valorGlosa": 5.23,
        "numRessarcimento": "",
        "codLote": 1820354,
        "parcela": 0
    },
    {
        "ano": 2021,
        "mes": 12,
        "tipoDespesa": "HOSPEDAGEM ,EXCETO DO PARLAMENTAR NO DISTRITO FEDERAL.",
        "codDocumento": 7323679,
        "tipoDocumento": "Nota Fiscal",
        "codTipoDocumento": 0,
        "dataDocumento": "2022-02-03",
        "numDocumento": "3247",
        "valorDocumento": 1054.8,
        "urlDocumento": "https://www.camara.leg.br/cota-parlamentar/documentos/publ/3034/2022/7323679.pdf",
        "nomeFornecedor": "POUSADA ARTE DA NATUREZA LTDA",
        "cnpjCpfFornecedor": "19853291000199",
        "valorLiquido": 1054.8,
        "valorGlosa": 0.0,
        "numRessarcimento": "",
        "codLote": 1825192,
        "parcela": 0
    },
    {
        "ano": 2021,
        "mes": 12,
        "tipoDespesa": "LOCAÇÃO OU FRETAMENTO DE VEÍCULOS AUTOMOTORES",
        "codDocumento": 7311546,
        "tipoDocumento": "Recibos/Outros",
        "codTipoDocumento": 1,
        "dataDocumento": "2021-12-01",
        "numDocumento": "003/2021",
        "valorDocumento": 8100.0,
        "urlDocumento": "https://www.camara.leg.br/cota-parlamentar/documentos/publ/3034/2021/7311546.pdf",
        "nomeFornecedor": "A & A AGRA LTDA",
        "cnpjCpfFornecedor": "12064991000155",
        "valorLiquido": 8100.0,
        "valorGlosa": 0.0,
        "numRessarcimento": "",
        "codLote": 1819340,
        "parcela": 0
    },
    {
        "ano": 2021,
        "mes": 12,
        "tipoDespesa": "SERVIÇO DE TÁXI, PEDÁGIO E ESTACIONAMENTO",
        "codDocumento": 7301135,
        "tipoDocumento": "Recibos/Outros",
        "codTipoDocumento": 1,
        "dataDocumento": "2021-12-02",
        "numDocumento": "s/n",
        "valorDocumento": 60.0,
        "urlDocumento": "https://www.camara.leg.br/cota-parlamentar/documentos/publ/3034/2021/7301135.pdf",
        "nomeFornecedor": "COOPERTAXI 202 NORTE",
        "cnpjCpfFornecedor": "08046163000117",
        "valorLiquido": 60.0,
        "valorGlosa": 0.0,
        "numRessarcimento": "",
        "codLote": 1814595,
        "parcela": 0
    },
    {
        "ano": 2021,
        "mes": 12,
        "tipoDespesa": "SERVIÇO DE TÁXI, PEDÁGIO E ESTACIONAMENTO",
        "codDocumento": 7302002,
        "tipoDocumento": "Recibos/Outros",
        "codTipoDocumento": 1,
        "dataDocumento": "2021-12-07",
        "numDocumento": "S/N",
        "valorDocumento": 40.0,
        "urlDocumento": "https://www.camara.leg.br/cota-parlamentar/documentos/publ/3034/2021/7302002.pdf",
        "nomeFornecedor": "COOPERTAXI 202 NORTE",
        "cnpjCpfFornecedor": "08046163000117",
        "valorLiquido": 40.0,
        "valorGlosa": 0.0,
        "numRessarcimento": "",
        "codLote": 1815046,
        "parcela": 0
    },
    {
        "ano": 2021,
        "mes": 12,
        "tipoDespesa": "SERVIÇO DE TÁXI, PEDÁGIO E ESTACIONAMENTO",
        "codDocumento": 7305403,
        "tipoDocumento": "Recibos/Outros",
        "codTipoDocumento": 1,
        "dataDocumento": "2021-12-14",
        "numDocumento": "S/N",
        "valorDocumento": 20.0,
        "urlDocumento": "https://www.camara.leg.br/cota-parlamentar/documentos/publ/3034/2021/7305403.pdf",
        "nomeFornecedor": "COOPERTAXI 202 NORTE",
        "cnpjCpfFornecedor": "08046163000117",
        "valorLiquido": 20.0,
        "valorGlosa": 0.0,
        "numRessarcimento": "",
        "codLote": 1816505,
        "parcela": 0
    },
    {
        "ano": 2021,
        "mes": 12,
        "tipoDespesa": "SERVIÇO DE TÁXI, PEDÁGIO E ESTACIONAMENTO",
        "codDocumento": 7308789,
        "tipoDocumento": "Recibos/Outros",
        "codTipoDocumento": 1,
        "dataDocumento": "2021-12-15",
        "numDocumento": "s/n",
        "valorDocumento": 40.0,
        "urlDocumento": "https://www.camara.leg.br/cota-parlamentar/documentos/publ/3034/2021/7308789.pdf",
        "nomeFornecedor": "COOPERTAXI 202 NORTE",
        "cnpjCpfFornecedor": "08046163000117",
        "valorLiquido": 40.0,
        "valorGlosa": 0.0,
        "numRessarcimento": "",
        "codLote": 1818076,
        "parcela": 0
    },
    {
        "ano": 2021,
        "mes": 12,
        "tipoDespesa": "SERVIÇO DE TÁXI, PEDÁGIO E ESTACIONAMENTO",
        "codDocumento": 7309925,
        "tipoDocumento": "Recibos/Outros",
        "codTipoDocumento": 1,
        "dataDocumento": "2021-12-21",
        "numDocumento": "s/n",
        "valorDocumento": 50.0,
        "urlDocumento": "https://www.camara.leg.br/cota-parlamentar/documentos/publ/3034/2021/7309925.pdf",
        "nomeFornecedor": "COOPERTAXI 202 NORTE",
        "cnpjCpfFornecedor": "08046163000117",
        "valorLiquido": 50.0,
        "valorGlosa": 0.0,
        "numRessarcimento": "",
        "codLote": 1818560,
        "parcela": 0
    },
    {
        "ano": 2021,
        "mes": 12,
        "tipoDespesa": "SERVIÇO DE TÁXI, PEDÁGIO E ESTACIONAMENTO",
        "codDocumento": 7309927,
        "tipoDocumento": "Recibos/Outros",
        "codTipoDocumento": 1,
        "dataDocumento": "2021-12-21",
        "numDocumento": "s/n",
        "valorDocumento": 70.0,
        "urlDocumento": "https://www.camara.leg.br/cota-parlamentar/documentos/publ/3034/2021/7309927.pdf",
        "nomeFornecedor": "COOPERTAXI 202 NORTE",
        "cnpjCpfFornecedor": "08046163000117",
        "valorLiquido": 70.0,
        "valorGlosa": 0.0,
        "numRessarcimento": "",
        "codLote": 1818561,
        "parcela": 0
    },
    {
        "ano": 2021,
        "mes": 12,
        "tipoDespesa": "SERVIÇO DE TÁXI, PEDÁGIO E ESTACIONAMENTO",
        "codDocumento": 7309846,
        "tipoDocumento": "Recibos/Outros",
        "codTipoDocumento": 1,
        "dataDocumento": "2021-12-21",
        "numDocumento": "S/N",
        "valorDocumento": 63.11,
        "urlDocumento": "https://www.camara.leg.br/cota-parlamentar/documentos/publ/3034/2021/7309846.pdf",
        "nomeFornecedor": "GGFF INTERMEDIACAO E NEGOCIO EM GERAL LTDA.",
        "cnpjCpfFornecedor": "33551388000178",
        "valorLiquido": 63.11,
        "valorGlosa": 0.0,
        "numRessarcimento": "",
        "codLote": 1818521,
        "parcela": 0
    },
    {
        "ano": 2021,
        "mes": 11,
        "tipoDespesa": "SERVIÇO DE TÁXI, PEDÁGIO E ESTACIONAMENTO",
        "codDocumento": 7295315,
        "tipoDocumento": "Recibos/Outros",
        "codTipoDocumento": 1,
        "dataDocumento": "2021-11-29",
        "numDocumento": "S/N",
        "valorDocumento": 63.08,
        "urlDocumento": "https://www.camara.leg.br/cota-parlamentar/documentos/publ/3034/2021/7295315.pdf",
        "nomeFornecedor": "SAFERTAXI",
        "cnpjCpfFornecedor": "12305217000199",
        "valorLiquido": 63.08,
        "valorGlosa": 0.0,
        "numRessarcimento": "",
        "codLote": 1811771,
        "parcela": 0
    },
    {
        "ano": 2021,
        "mes": 12,
        "tipoDespesa": "SERVIÇO DE TÁXI, PEDÁGIO E ESTACIONAMENTO",
        "codDocumento": 7308794,
        "tipoDocumento": "Recibos/Outros",
        "codTipoDocumento": 1,
        "dataDocumento": "2021-12-14",
        "numDocumento": "s/n",
        "valorDocumento": 64.0,
        "urlDocumento": "https://www.camara.leg.br/cota-parlamentar/documentos/publ/3034/2021/7308794.pdf",
        "nomeFornecedor": "SAFERTAXI",
        "cnpjCpfFornecedor": "12305217000199",
        "valorLiquido": 64.0,
        "valorGlosa": 0.0,
        "numRessarcimento": "",
        "codLote": 1818079,
        "parcela": 0
    },
    {
        "ano": 2021,
        "mes": 12,
        "tipoDespesa": "SERVIÇO DE TÁXI, PEDÁGIO E ESTACIONAMENTO",
        "codDocumento": 7305393,
        "tipoDocumento": "Recibos/Outros",
        "codTipoDocumento": 1,
        "dataDocumento": "2021-12-14",
        "numDocumento": "S/N",
        "valorDocumento": 20.0,
        "urlDocumento": "https://www.camara.leg.br/cota-parlamentar/documentos/publ/3034/2021/7305393.pdf",
        "nomeFornecedor": "SINPETAXI",
        "cnpjCpfFornecedor": "00031708000100",
        "valorLiquido": 20.0,
        "valorGlosa": 0.0,
        "numRessarcimento": "",
        "codLote": 1816497,
        "parcela": 0
    },
    {
        "ano": 2021,
        "mes": 12,
        "tipoDespesa": "SERVIÇO DE TÁXI, PEDÁGIO E ESTACIONAMENTO",
        "codDocumento": 7305375,
        "tipoDocumento": "Recibos/Outros",
        "codTipoDocumento": 1,
        "dataDocumento": "2021-12-13",
        "numDocumento": "S/N",
        "valorDocumento": 20.0,
        "urlDocumento": "https://www.camara.leg.br/cota-parlamentar/documentos/publ/3034/2021/7305375.pdf",
        "nomeFornecedor": "TÁXI LEGAL",
        "cnpjCpfFornecedor": "30605977000101",
        "valorLiquido": 20.0,
        "valorGlosa": 0.0,
        "numRessarcimento": "",
        "codLote": 1816494,
        "parcela": 0
    },
    {
        "ano": 2021,
        "mes": 12,
        "tipoDespesa": "PASSAGEM AÉREA - SIGEPA",
        "codDocumento": 66398,
        "tipoDocumento": "Nota Fiscal",
        "codTipoDocumento": 0,
        "dataDocumento": "2021-12-08",
        "numDocumento": "1272165521730",
        "valorDocumento": 1370.89,
        "urlDocumento": null,
        "nomeFornecedor": "GOL",
        "cnpjCpfFornecedor": "",
        "valorLiquido": 1370.89,
        "valorGlosa": 0.0,
        "numRessarcimento": "0",
        "codLote": 0,
        "parcela": 0
    },
    {
        "ano": 2021,
        "mes": 12,
        "tipoDespesa": "PASSAGEM AÉREA - SIGEPA",
        "codDocumento": 66407,
        "tipoDocumento": "Nota Fiscal",
        "codTipoDocumento": 0,
        "dataDocumento": "2021-12-08",
        "numDocumento": "1272165522908",
        "valorDocumento": 327.96,
        "urlDocumento": null,
        "nomeFornecedor": "GOL",
        "cnpjCpfFornecedor": "",
        "valorLiquido": 327.96,
        "valorGlosa": 0.0,
        "numRessarcimento": "0",
        "codLote": 0,
        "parcela": 0
    },
    {
        "ano": 2021,
        "mes": 12,
        "tipoDespesa": "PASSAGEM AÉREA - SIGEPA",
        "codDocumento": 66994,
        "tipoDocumento": "Nota Fiscal",
        "codTipoDocumento": 0,
        "dataDocumento": "2021-12-09",
        "numDocumento": "1272165619382",
        "valorDocumento": 461.03,
        "urlDocumento": null,
        "nomeFornecedor": "GOL",
        "cnpjCpfFornecedor": "",
        "valorLiquido": 461.03,
        "valorGlosa": 0.0,
        "numRessarcimento": "0",
        "codLote": 0,
        "parcela": 0
    },
    {
        "ano": 2021,
        "mes": 12,
        "tipoDespesa": "PASSAGEM AÉREA - SIGEPA",
        "codDocumento": 68425,
        "tipoDocumento": "Nota Fiscal",
        "codTipoDocumento": 0,
        "dataDocumento": "2021-12-19",
        "numDocumento": "1272166229902",
        "valorDocumento": 458.17,
        "urlDocumento": null,
        "nomeFornecedor": "GOL",
        "cnpjCpfFornecedor": "",
        "valorLiquido": 458.17,
        "valorGlosa": 0.0,
        "numRessarcimento": "0",
        "codLote": 0,
        "parcela": 0
    },
    {
        "ano": 2021,
        "mes": 12,
        "tipoDespesa": "PASSAGEM AÉREA - SIGEPA",
        "codDocumento": 68426,
        "tipoDocumento": "Nota Fiscal",
        "codTipoDocumento": 0,
        "dataDocumento": "2021-12-19",
        "numDocumento": "1272166229930",
        "valorDocumento": 461.03,
        "urlDocumento": null,
        "nomeFornecedor": "GOL",
        "cnpjCpfFornecedor": "",
        "valorLiquido": 461.03,
        "valorGlosa": 0.0,
        "numRessarcimento": "0",
        "codLote": 0,
        "parcela": 0
    },
    {
        "ano": 2021,
        "mes": 12,
        "tipoDespesa": "PASSAGEM AÉREA - SIGEPA",
        "codDocumento": 68607,
        "tipoDocumento": "Nota Fiscal",
        "codTipoDocumento": 0,
        "dataDocumento": "2021-12-21",
        "numDocumento": "1272166362016",
        "valorDocumento": 523.11,
        "urlDocumento": null,
        "nomeFornecedor": "GOL",
        "cnpjCpfFornecedor": "",
        "valorLiquido": 523.11,
        "valorGlosa": 0.0,
        "numRessarcimento": "0",
        "codLote": 0,
        "parcela": 0
    },
    {
        "ano": 2021,
        "mes": 11,
        "tipoDespesa": "PASSAGEM AÉREA - SIGEPA",
        "codDocumento": 61573,
        "tipoDocumento": "Nota Fiscal",
        "codTipoDocumento": 0,
        "dataDocumento": "2021-11-11",
        "numDocumento": "9572160968263",
        "valorDocumento": 49.0,
        "urlDocumento": null,
        "nomeFornecedor": "TAM",
        "cnpjCpfFornecedor": "",
        "valorLiquido": 49.0,
        "valorGlosa": 0.0,
        "numRessarcimento": "0",
        "codLote": 0,
        "parcela": 0
    },
    {
        "ano": 2021,
        "mes": 11,
        "tipoDespesa": "PASSAGEM AÉREA - SIGEPA",
        "codDocumento": 61573,
        "tipoDocumento": "Nota Fiscal",
        "codTipoDocumento": 0,
        "dataDocumento": "2021-11-11",
        "numDocumento": "9572160968263",
        "valorDocumento": 1225.18,
        "urlDocumento": null,
        "nomeFornecedor": "TAM",
        "cnpjCpfFornecedor": "",
        "valorLiquido": 1225.18,
        "valorGlosa": 0.0,
        "numRessarcimento": "0",
        "codLote": 0,
        "parcela": 0
    },
    {
        "ano": 2021,
        "mes": 11,
        "tipoDespesa": "PASSAGEM AÉREA - SIGEPA",
        "codDocumento": 61979,
        "tipoDocumento": "Nota Fiscal",
        "codTipoDocumento": 0,
        "dataDocumento": "2021-11-16",
        "numDocumento": "9572161334951",
        "valorDocumento": 69.0,
        "urlDocumento": null,
        "nomeFornecedor": "TAM",
        "cnpjCpfFornecedor": "",
        "valorLiquido": 69.0,
        "valorGlosa": 0.0,
        "numRessarcimento": "0",
        "codLote": 0,
        "parcela": 0
    },
    {
        "ano": 2021,
        "mes": 11,
        "tipoDespesa": "PASSAGEM AÉREA - SIGEPA",
        "codDocumento": 61979,
        "tipoDocumento": "Nota Fiscal",
        "codTipoDocumento": 0,
        "dataDocumento": "2021-11-16",
        "numDocumento": "9572161334951",
        "valorDocumento": 1415.33,
        "urlDocumento": null,
        "nomeFornecedor": "TAM",
        "cnpjCpfFornecedor": "",
        "valorLiquido": 1415.33,
        "valorGlosa": 0.0,
        "numRessarcimento": "0",
        "codLote": 0,
        "parcela": 0
    },
    {
        "ano": 2021,
        "mes": 11,
        "tipoDespesa": "PASSAGEM AÉREA - SIGEPA",
        "codDocumento": 61983,
        "tipoDocumento": "Nota Fiscal",
        "codTipoDocumento": 0,
        "dataDocumento": "2021-11-16",
        "numDocumento": "9572161337328",
        "valorDocumento": 49.0,
        "urlDocumento": null,
        "nomeFornecedor": "TAM",
        "cnpjCpfFornecedor": "",
        "valorLiquido": 49.0,
        "valorGlosa": 0.0,
        "numRessarcimento": "0",
        "codLote": 0,
        "parcela": 0
    },
    {
        "ano": 2021,
        "mes": 11,
        "tipoDespesa": "PASSAGEM AÉREA - SIGEPA",
        "codDocumento": 61983,
        "tipoDocumento": "Nota Fiscal",
        "codTipoDocumento": 0,
        "dataDocumento": "2021-11-16",
        "numDocumento": "9572161337328",
        "valorDocumento": 1421.33,
        "urlDocumento": null,
        "nomeFornecedor": "TAM",
        "cnpjCpfFornecedor": "",
        "valorLiquido": 1421.33,
        "valorGlosa": 0.0,
        "numRessarcimento": "0",
        "codLote": 0,
        "parcela": 0
    },
    {
        "ano": 2021,
        "mes": 11,
        "tipoDespesa": "PASSAGEM AÉREA - SIGEPA",
        "codDocumento": 62250,
        "tipoDocumento": "Nota Fiscal",
        "codTipoDocumento": 0,
        "dataDocumento": "2021-11-17",
        "numDocumento": "9572161427077",
        "valorDocumento": 49.0,
        "urlDocumento": null,
        "nomeFornecedor": "TAM",
        "cnpjCpfFornecedor": "",
        "valorLiquido": 49.0,
        "valorGlosa": 0.0,
        "numRessarcimento": "0",
        "codLote": 0,
        "parcela": 0
    },
    {
        "ano": 2021,
        "mes": 11,
        "tipoDespesa": "PASSAGEM AÉREA - SIGEPA",
        "codDocumento": 62250,
        "tipoDocumento": "Nota Fiscal",
        "codTipoDocumento": 0,
        "dataDocumento": "2021-11-17",
        "numDocumento": "9572161427077",
        "valorDocumento": 1421.33,
        "urlDocumento": null,
        "nomeFornecedor": "TAM",
        "cnpjCpfFornecedor": "",
        "valorLiquido": 1421.33,
        "valorGlosa": 0.0,
        "numRessarcimento": "0",
        "codLote": 0,
        "parcela": 0
    },
    {
        "ano": 2021,
        "mes": 11,
        "tipoDespesa": "PASSAGEM AÉREA - SIGEPA",
        "codDocumento": 62266,
        "tipoDocumento": "Nota Fiscal",
        "codTipoDocumento": 0,
        "dataDocumento": "2021-11-17",
        "numDocumento": "9572161430045",
        "valorDocumento": 49.0,
        "urlDocumento": null,
        "nomeFornecedor": "TAM",
        "cnpjCpfFornecedor": "",
        "valorLiquido": 49.0,
        "valorGlosa": 0.0,
        "numRessarcimento": "0",
        "codLote": 0,
        "parcela": 0
    },
    {
        "ano": 2021,
        "mes": 11,
        "tipoDespesa": "PASSAGEM AÉREA - SIGEPA",
        "codDocumento": 62266,
        "tipoDocumento": "Nota Fiscal",
        "codTipoDocumento": 0,
        "dataDocumento": "2021-11-17",
        "numDocumento": "9572161430045",
        "valorDocumento": 616.23,
        "urlDocumento": null,
        "nomeFornecedor": "TAM",
        "cnpjCpfFornecedor": "",
        "valorLiquido": 616.23,
        "valorGlosa": 0.0,
        "numRessarcimento": "0",
        "codLote": 0,
        "parcela": 0
    },
    {
        "ano": 2021,
        "mes": 11,
        "tipoDespesa": "PASSAGEM AÉREA - SIGEPA",
        "codDocumento": 63658,
        "tipoDocumento": "Nota Fiscal",
        "codTipoDocumento": 0,
        "dataDocumento": "2021-11-24",
        "numDocumento": "9572162077004",
        "valorDocumento": 49.0,
        "urlDocumento": null,
        "nomeFornecedor": "TAM",
        "cnpjCpfFornecedor": "",
        "valorLiquido": 49.0,
        "valorGlosa": 0.0,
        "numRessarcimento": "0",
        "codLote": 0,
        "parcela": 0
    },
    {
        "ano": 2021,
        "mes": 11,
        "tipoDespesa": "PASSAGEM AÉREA - SIGEPA",
        "codDocumento": 63658,
        "tipoDocumento": "Nota Fiscal",
        "codTipoDocumento": 0,
        "dataDocumento": "2021-11-24",
        "numDocumento": "9572162077004",
        "valorDocumento": 897.35,
        "urlDocumento": null,
        "nomeFornecedor": "TAM",
        "cnpjCpfFornecedor": "",
        "valorLiquido": 897.35,
        "valorGlosa": 0.0,
        "numRessarcimento": "0",
        "codLote": 0,
        "parcela": 0
    },
    {
        "ano": 2021,
        "mes": 11,
        "tipoDespesa": "PASSAGEM AÉREA - SIGEPA",
        "codDocumento": 64550,
        "tipoDocumento": "Nota Fiscal",
        "codTipoDocumento": 0,
        "dataDocumento": "2021-11-30",
        "numDocumento": "9572162759554",
        "valorDocumento": 49.0,
        "urlDocumento": null,
        "nomeFornecedor": "TAM",
        "cnpjCpfFornecedor": "",
        "valorLiquido": 49.0,
        "valorGlosa": 0.0,
        "numRessarcimento": "0",
        "codLote": 0,
        "parcela": 0
    },
    {
        "ano": 2021,
        "mes": 11,
        "tipoDespesa": "PASSAGEM AÉREA - SIGEPA",
        "codDocumento": 64550,
        "tipoDocumento": "Nota Fiscal",
        "codTipoDocumento": 0,
        "dataDocumento": "2021-11-30",
        "numDocumento": "9572162759554",
        "valorDocumento": 903.35,
        "urlDocumento": null,
        "nomeFornecedor": "TAM",
        "cnpjCpfFornecedor": "",
        "valorLiquido": 903.35,
        "valorGlosa": 0.0,
        "numRessarcimento": "0",
        "codLote": 0,
        "parcela": 0
    },
    {
        "ano": 2021,
        "mes": 12,
        "tipoDespesa": "PASSAGEM AÉREA - SIGEPA",
        "codDocumento": 66116,
        "tipoDocumento": "Nota Fiscal",
        "codTipoDocumento": 0,
        "dataDocumento": "2021-12-07",
        "numDocumento": "9572163331591",
        "valorDocumento": 55.0,
        "urlDocumento": null,
        "nomeFornecedor": "TAM",
        "cnpjCpfFornecedor": "",
        "valorLiquido": 55.0,
        "valorGlosa": 0.0,
        "numRessarcimento": "0",
        "codLote": 0,
        "parcela": 0
    },
    {
        "ano": 2021,
        "mes": 12,
        "tipoDespesa": "PASSAGEM AÉREA - SIGEPA",
        "codDocumento": 66116,
        "tipoDocumento": "Nota Fiscal",
        "codTipoDocumento": 0,
        "dataDocumento": "2021-12-07",
        "numDocumento": "9572163331591",
        "valorDocumento": 1695.66,
        "urlDocumento": null,
        "nomeFornecedor": "TAM",
        "cnpjCpfFornecedor": "",
        "valorLiquido": 1695.66,
        "valorGlosa": 0.0,
        "numRessarcimento": "0",
        "codLote": 0,
        "parcela": 0
    },
    {
        "ano": 2021,
        "mes": 12,
        "tipoDespesa": "PASSAGEM AÉREA - SIGEPA",
        "codDocumento": 67435,
        "tipoDocumento": "Nota Fiscal",
        "codTipoDocumento": 0,
        "dataDocumento": "2021-12-13",
        "numDocumento": "9572163821070",
        "valorDocumento": 461.03,
        "urlDocumento": null,
        "nomeFornecedor": "TAM",
        "cnpjCpfFornecedor": "",
        "valorLiquido": 461.03,
        "valorGlosa": 0.0,
        "numRessarcimento": "0",
        "codLote": 0,
        "parcela": 0
    },
    {
        "ano": 2021,
        "mes": 12,
        "tipoDespesa": "PASSAGEM AÉREA - RPA",
        "codDocumento": 1760533,
        "tipoDocumento": "Nota Fiscal",
        "codTipoDocumento": 0,
        "dataDocumento": "2021-12-09",
        "numDocumento": "Bilhete: SKD6MQ",
        "valorDocumento": 2228.87,
        "urlDocumento": null,
        "nomeFornecedor": "Cia Aérea - AZUL",
        "cnpjCpfFornecedor": "09296295000160",
        "valorLiquido": 2228.87,
        "valorGlosa": 0.0,
        "numRessarcimento": "0",
        "codLote": 0,
        "parcela": 0
    },
    {
        "ano": 2022,
        "mes": 1,
        "tipoDespesa": "MANUTENÇÃO DE ESCRITÓRIO DE APOIO À ATIVIDADE PARLAMENTAR",
        "codDocumento": 7320084,
        "tipoDocumento": "Recibos/Outros",
        "codTipoDocumento": 1,
        "dataDocumento": "2022-01-27",
        "numDocumento": "0512",
        "valorDocumento": 3500.0,
        "urlDocumento": "https://www.camara.leg.br/cota-parlamentar/documentos/publ/3034/2022/7320084.pdf",
        "nomeFornecedor": "ERIKA FERREIRA LOO LI",
        "cnpjCpfFornecedor": "34180303272",
        "valorLiquido": 3500.0,
        "valorGlosa": 0.0,
        "numRessarcimento": "",
        "codLote": 1823466,
        "parcela": 0
    },
    {
        "ano": 2022,
        "mes": 2,
        "tipoDespesa": "MANUTENÇÃO DE ESCRITÓRIO DE APOIO À ATIVIDADE PARLAMENTAR",
        "codDocumento": 7335680,
        "tipoDocumento": "Recibos/Outros",
        "codTipoDocumento": 1,
        "dataDocumento": "2022-02-28",
        "numDocumento": "0612",
        "valorDocumento": 3500.0,
        "urlDocumento": "https://www.camara.leg.br/cota-parlamentar/documentos/publ/3034/2022/7335680.pdf",
        "nomeFornecedor": "ERIKA FERREIRA LOO LI",
        "cnpjCpfFornecedor": "34180303272",
        "valorLiquido": 3500.0,
        "valorGlosa": 0.0,
        "numRessarcimento": "",
        "codLote": 1830813,
        "parcela": 0
    },
    {
        "ano": 2022,
        "mes": 3,
        "tipoDespesa": "MANUTENÇÃO DE ESCRITÓRIO DE APOIO À ATIVIDADE PARLAMENTAR",
        "codDocumento": 7355279,
        "tipoDocumento": "Recibos/Outros",
        "codTipoDocumento": 1,
        "dataDocumento": "2022-02-28",
        "numDocumento": "0712",
        "valorDocumento": 3500.0,
        "urlDocumento": "https://www.camara.leg.br/cota-parlamentar/documentos/publ/3034/2022/7355279.pdf",
        "nomeFornecedor": "ERIKA FERREIRA LOO LI",
        "cnpjCpfFornecedor": "34180303272",
        "valorLiquido": 3500.0,
        "valorGlosa": 0.0,
        "numRessarcimento": "",
        "codLote": 1840192,
        "parcela": 0
    },
    {
        "ano": 2022,
        "mes": 4,
        "tipoDespesa": "MANUTENÇÃO DE ESCRITÓRIO DE APOIO À ATIVIDADE PARLAMENTAR",
        "codDocumento": 7375020,
        "tipoDocumento": "Recibos/Outros",
        "codTipoDocumento": 1,
        "dataDocumento": "2022-04-28",
        "numDocumento": "08",
        "valorDocumento": 3500.0,
        "urlDocumento": "https://www.camara.leg.br/cota-parlamentar/documentos/publ/3034/2022/7375020.pdf",
        "nomeFornecedor": "ERIKA FERREIRA LOO LI",
        "cnpjCpfFornecedor": "34180303272",
        "valorLiquido": 3500.0,
        "valorGlosa": 0.0,
        "numRessarcimento": "",
        "codLote": 1850665,
        "parcela": 0
    },
    {
        "ano": 2022,
        "mes": 4,
        "tipoDespesa": "MANUTENÇÃO DE ESCRITÓRIO DE APOIO À ATIVIDADE PARLAMENTAR",
        "codDocumento": 7363257,
        "tipoDocumento": "Nota Fiscal Eletrônica",
        "codTipoDocumento": 4,
        "dataDocumento": "2022-04-11",
        "numDocumento": "644",
        "valorDocumento": 3800.0,
        "urlDocumento": "http://camara.leg.br/cota-parlamentar/nota-fiscal-eletronica?ideDocumentoFiscal=7363257",
        "nomeFornecedor": "R S IGLESIAS",
        "cnpjCpfFornecedor": "01067007000193",
        "valorLiquido": 3590.0,
        "valorGlosa": 210.0,
        "numRessarcimento": "",
        "codLote": 1844474,
        "parcela": 0
    },
    {
        "ano": 2022,
        "mes": 4,
        "tipoDespesa": "COMBUSTÍVEIS E LUBRIFICANTES.",
        "codDocumento": 7372394,
        "tipoDocumento": "Nota Fiscal Eletrônica",
        "codTipoDocumento": 4,
        "dataDocumento": "2022-04-30",
        "numDocumento": "4859",
        "valorDocumento": 1637.23,
        "urlDocumento": "http://camara.leg.br/cota-parlamentar/nota-fiscal-eletronica?ideDocumentoFiscal=7372394",
        "nomeFornecedor": "AEROPOSTO COMBUSTIVEIS AUTOMOTIVO LTDA",
        "cnpjCpfFornecedor": "08580311000189",
        "valorLiquido": 1637.23,
        "valorGlosa": 0.0,
        "numRessarcimento": "",
        "codLote": 1848366,
        "parcela": 0
    },
    {
        "ano": 2022,
        "mes": 2,
        "tipoDespesa": "COMBUSTÍVEIS E LUBRIFICANTES.",
        "codDocumento": 7331224,
        "tipoDocumento": "Nota Fiscal Eletrônica",
        "codTipoDocumento": 4,
        "dataDocumento": "2022-02-16",
        "numDocumento": "15794",
        "valorDocumento": 370.82,
        "urlDocumento": "http://camara.leg.br/cota-parlamentar/nota-fiscal-eletronica?ideDocumentoFiscal=7331224",
        "nomeFornecedor": "AUTO POSTO 306 NORTE LTDA",
        "cnpjCpfFornecedor": "22398818000147",
        "valorLiquido": 370.82,
        "valorGlosa": 0.0,
        "numRessarcimento": "",
        "codLote": 1828802,
        "parcela": 0
    },
    {
        "ano": 2022,
        "mes": 5,
        "tipoDespesa": "COMBUSTÍVEIS E LUBRIFICANTES.",
        "codDocumento": 7373700,
        "tipoDocumento": "Nota Fiscal Eletrônica",
        "codTipoDocumento": 4,
        "dataDocumento": "2022-05-01",
        "numDocumento": "105298",
        "valorDocumento": 500.05,
        "urlDocumento": "http://camara.leg.br/cota-parlamentar/nota-fiscal-eletronica?ideDocumentoFiscal=7373700",
        "nomeFornecedor": "MACHADO  ANDRADE LTDA",
        "cnpjCpfFornecedor": "08945482000164",
        "valorLiquido": 500.05,
        "valorGlosa": 0.0,
        "numRessarcimento": "",
        "codLote": 1849985,
        "parcela": 0
    },
    {
        "ano": 2022,
        "mes": 1,
        "tipoDespesa": "COMBUSTÍVEIS E LUBRIFICANTES.",
        "codDocumento": 7314509,
        "tipoDocumento": "Nota Fiscal Eletrônica",
        "codTipoDocumento": 4,
        "dataDocumento": "2022-01-10",
        "numDocumento": "2668",
        "valorDocumento": 1823.0,
        "urlDocumento": "http://camara.leg.br/cota-parlamentar/nota-fiscal-eletronica?ideDocumentoFiscal=7314509",
        "nomeFornecedor": "R  R EMPREENDIMENTOS EIRELI EPP",
        "cnpjCpfFornecedor": "10929612000117",
        "valorLiquido": 1823.0,
        "valorGlosa": 0.0,
        "numRessarcimento": "",
        "codLote": 1820793,
        "parcela": 0
    },
    {
        "ano": 2022,
        "mes": 1,
        "tipoDespesa": "COMBUSTÍVEIS E LUBRIFICANTES.",
        "codDocumento": 7319234,
        "tipoDocumento": "Nota Fiscal Eletrônica",
        "codTipoDocumento": 4,
        "dataDocumento": "2022-01-25",
        "numDocumento": "2677",
        "valorDocumento": 1436.4,
        "urlDocumento": "http://camara.leg.br/cota-parlamentar/nota-fiscal-eletronica?ideDocumentoFiscal=7319234",
        "nomeFornecedor": "R  R EMPREENDIMENTOS EIRELI EPP",
        "cnpjCpfFornecedor": "10929612000117",
        "valorLiquido": 1436.4,
        "valorGlosa": 0.0,
        "numRessarcimento": "",
        "codLote": 1823042,
        "parcela": 0
    },
    {
        "ano": 2022,
        "mes": 2,
        "tipoDespesa": "COMBUSTÍVEIS E LUBRIFICANTES.",
        "codDocumento": 7335507,
        "tipoDocumento": "Nota Fiscal Eletrônica",
        "codTipoDocumento": 4,
        "dataDocumento": "2022-02-25",
        "numDocumento": "2703",
        "valorDocumento": 4128.65,
        "urlDocumento": "http://camara.leg.br/cota-parlamentar/nota-fiscal-eletronica?ideDocumentoFiscal=7335507",
        "nomeFornecedor": "R  R EMPREENDIMENTOS EIRELI EPP",
        "cnpjCpfFornecedor": "10929612000117",
        "valorLiquido": 4128.65,
        "valorGlosa": 0.0,
        "numRessarcimento": "",
        "codLote": 1830723,
        "parcela": 0
    },
    {
        "ano": 2022,
        "mes": 3,
        "tipoDespesa": "COMBUSTÍVEIS E LUBRIFICANTES.",
        "codDocumento": 7344406,
        "tipoDocumento": "Nota Fiscal Eletrônica",
        "codTipoDocumento": 4,
        "dataDocumento": "2022-03-15",
        "numDocumento": "2718",
        "valorDocumento": 3024.32,
        "urlDocumento": "http://camara.leg.br/cota-parlamentar/nota-fiscal-eletronica?ideDocumentoFiscal=7344406",
        "nomeFornecedor": "R  R EMPREENDIMENTOS EIRELI EPP",
        "cnpjCpfFornecedor": "10929612000117",
        "valorLiquido": 3024.32,
        "valorGlosa": 0.0,
        "numRessarcimento": "",
        "codLote": 1834894,
        "parcela": 0
    },
    {
        "ano": 2022,
        "mes": 3,
        "tipoDespesa": "COMBUSTÍVEIS E LUBRIFICANTES.",
        "codDocumento": 7355583,
        "tipoDocumento": "Nota Fiscal Eletrônica",
        "codTipoDocumento": 4,
        "dataDocumento": "2022-03-28",
        "numDocumento": "2728",
        "valorDocumento": 1783.4,
        "urlDocumento": "http://camara.leg.br/cota-parlamentar/nota-fiscal-eletronica?ideDocumentoFiscal=7355583",
        "nomeFornecedor": "R  R EMPREENDIMENTOS EIRELI EPP",
        "cnpjCpfFornecedor": "10929612000117",
        "valorLiquido": 1783.4,
        "valorGlosa": 0.0,
        "numRessarcimento": "",
        "codLote": 1840341,
        "parcela": 0
    },
    {
        "ano": 2022,
        "mes": 4,
        "tipoDespesa": "COMBUSTÍVEIS E LUBRIFICANTES.",
        "codDocumento": 7365180,
        "tipoDocumento": "Nota Fiscal Eletrônica",
        "codTipoDocumento": 4,
        "dataDocumento": "2022-04-14",
        "numDocumento": "2738",
        "valorDocumento": 2571.44,
        "urlDocumento": "http://camara.leg.br/cota-parlamentar/nota-fiscal-eletronica?ideDocumentoFiscal=7365180",
        "nomeFornecedor": "R  R EMPREENDIMENTOS EIRELI EPP",
        "cnpjCpfFornecedor": "10929612000117",
        "valorLiquido": 2571.44,
        "valorGlosa": 0.0,
        "numRessarcimento": "",
        "codLote": 1845256,
        "parcela": 0
    },
    {
        "ano": 2022,
        "mes": 1,
        "tipoDespesa": "COMBUSTÍVEIS E LUBRIFICANTES.",
        "codDocumento": 7319238,
        "tipoDocumento": "Nota Fiscal Eletrônica",
        "codTipoDocumento": 4,
        "dataDocumento": "2022-01-25",
        "numDocumento": "1001",
        "valorDocumento": 2195.64,
        "urlDocumento": "http://camara.leg.br/cota-parlamentar/nota-fiscal-eletronica?ideDocumentoFiscal=7319238",
        "nomeFornecedor": "RR EMPREENDIMENTOS EIRELLIEPP",
        "cnpjCpfFornecedor": "10929612000460",
        "valorLiquido": 2195.64,
        "valorGlosa": 0.0,
        "numRessarcimento": "",
        "codLote": 1823042,
        "parcela": 0
    },
    {
        "ano": 2022,
        "mes": 2,
        "tipoDespesa": "COMBUSTÍVEIS E LUBRIFICANTES.",
        "codDocumento": 7327611,
        "tipoDocumento": "Nota Fiscal Eletrônica",
        "codTipoDocumento": 4,
        "dataDocumento": "2022-02-10",
        "numDocumento": "1003",
        "valorDocumento": 1441.05,
        "urlDocumento": "http://camara.leg.br/cota-parlamentar/nota-fiscal-eletronica?ideDocumentoFiscal=7327611",
        "nomeFornecedor": "RR EMPREENDIMENTOS EIRELLIEPP",
        "cnpjCpfFornecedor": "10929612000460",
        "valorLiquido": 1441.05,
        "valorGlosa": 0.0,
        "numRessarcimento": "",
        "codLote": 1827114,
        "parcela": 0
    },
    {
        "ano": 2022,
        "mes": 3,
        "tipoDespesa": "COMBUSTÍVEIS E LUBRIFICANTES.",
        "codDocumento": 7355594,
        "tipoDocumento": "Nota Fiscal Eletrônica",
        "codTipoDocumento": 4,
        "dataDocumento": "2022-03-28",
        "numDocumento": "1025",
        "valorDocumento": 1190.78,
        "urlDocumento": "http://camara.leg.br/cota-parlamentar/nota-fiscal-eletronica?ideDocumentoFiscal=7355594",
        "nomeFornecedor": "RR EMPREENDIMENTOS EIRELLIEPP",
        "cnpjCpfFornecedor": "10929612000460",
        "valorLiquido": 1190.78,
        "valorGlosa": 0.0,
        "numRessarcimento": "",
        "codLote": 1840348,
        "parcela": 0
    },
    {
        "ano": 2022,
        "mes": 4,
        "tipoDespesa": "COMBUSTÍVEIS E LUBRIFICANTES.",
        "codDocumento": 7365173,
        "tipoDocumento": "Nota Fiscal Eletrônica",
        "codTipoDocumento": 4,
        "dataDocumento": "2022-04-14",
        "numDocumento": "1031",
        "valorDocumento": 1767.93,
        "urlDocumento": "http://camara.leg.br/cota-parlamentar/nota-fiscal-eletronica?ideDocumentoFiscal=7365173",
        "nomeFornecedor": "RR EMPREENDIMENTOS EIRELLIEPP",
        "cnpjCpfFornecedor": "10929612000460",
        "valorLiquido": 1767.93,
        "valorGlosa": 0.0,
        "numRessarcimento": "",
        "codLote": 1845252,
        "parcela": 0
    },
    {
        "ano": 2022,
        "mes": 5,
        "tipoDespesa": "COMBUSTÍVEIS E LUBRIFICANTES.",
        "codDocumento": 7373670,
        "tipoDocumento": "Nota Fiscal Eletrônica",
        "codTipoDocumento": 4,
        "dataDocumento": "2022-05-03",
        "numDocumento": "363699",
        "valorDocumento": 500.11,
        "urlDocumento": "http://camara.leg.br/cota-parlamentar/nota-fiscal-eletronica?ideDocumentoFiscal=7373670",
        "nomeFornecedor": "SOUZA & CAVALCANTE COMERCIO LTDA",
        "cnpjCpfFornecedor": "02163903000119",
        "valorLiquido": 500.11,
        "valorGlosa": 0.0,
        "numRessarcimento": "",
        "codLote": 1849970,
        "parcela": 0
    },
    {
        "ano": 2022,
        "mes": 3,
        "tipoDespesa": "DIVULGAÇÃO DA ATIVIDADE PARLAMENTAR.",
        "codDocumento": 7350454,
        "tipoDocumento": "Nota Fiscal",
        "codTipoDocumento": 0,
        "dataDocumento": "2022-03-24",
        "numDocumento": "202200000000377",
        "valorDocumento": 3000.0,
        "urlDocumento": "https://www.camara.leg.br/cota-parlamentar/documentos/publ/3034/2022/7350454.pdf",
        "nomeFornecedor": "BEIJA FLOR RADIODIFUSÃO LTDA",
        "cnpjCpfFornecedor": "00881907000611",
        "valorLiquido": 3000.0,
        "valorGlosa": 0.0,
        "numRessarcimento": "",
        "codLote": 1837597,
        "parcela": 0
    },
    {
        "ano": 2022,
        "mes": 1,
        "tipoDespesa": "DIVULGAÇÃO DA ATIVIDADE PARLAMENTAR.",
        "codDocumento": 7334770,
        "tipoDocumento": "Nota Fiscal Eletrônica",
        "codTipoDocumento": 4,
        "dataDocumento": "2022-02-24",
        "numDocumento": "301",
        "valorDocumento": 2000.0,
        "urlDocumento": "http://camara.leg.br/cota-parlamentar/nota-fiscal-eletronica?ideDocumentoFiscal=7334770",
        "nomeFornecedor": "CLAUDIO GOMES DA SILVA",
        "cnpjCpfFornecedor": "20357070000109",
        "valorLiquido": 2000.0,
        "valorGlosa": 0.0,
        "numRessarcimento": "",
        "codLote": 1830415,
        "parcela": 0
    },
    {
        "ano": 2022,
        "mes": 2,
        "tipoDespesa": "DIVULGAÇÃO DA ATIVIDADE PARLAMENTAR.",
        "codDocumento": 7348792,
        "tipoDocumento": "Nota Fiscal Eletrônica",
        "codTipoDocumento": 4,
        "dataDocumento": "2022-03-09",
        "numDocumento": "305",
        "valorDocumento": 2000.0,
        "urlDocumento": "http://camara.leg.br/cota-parlamentar/nota-fiscal-eletronica?ideDocumentoFiscal=7348792",
        "nomeFornecedor": "CLAUDIO GOMES DA SILVA ME",
        "cnpjCpfFornecedor": "20357070000109",
        "valorLiquido": 2000.0,
        "valorGlosa": 0.0,
        "numRessarcimento": "",
        "codLote": 1836902,
        "parcela": 0
    },
    {
        "ano": 2022,
        "mes": 1,
        "tipoDespesa": "DIVULGAÇÃO DA ATIVIDADE PARLAMENTAR.",
        "codDocumento": 7321472,
        "tipoDocumento": "Nota Fiscal",
        "codTipoDocumento": 0,
        "dataDocumento": "2022-01-31",
        "numDocumento": "202200000000127",
        "valorDocumento": 15000.0,
        "urlDocumento": "https://www.camara.leg.br/cota-parlamentar/documentos/publ/3034/2022/7321472.pdf",
        "nomeFornecedor": "K.D DA SILVA GOES",
        "cnpjCpfFornecedor": "32756633000110",
        "valorLiquido": 15000.0,
        "valorGlosa": 0.0,
        "numRessarcimento": "",
        "codLote": 1824141,
        "parcela": 0
    },
    {
        "ano": 2022,
        "mes": 2,
        "tipoDespesa": "DIVULGAÇÃO DA ATIVIDADE PARLAMENTAR.",
        "codDocumento": 7335578,
        "tipoDocumento": "Nota Fiscal",
        "codTipoDocumento": 0,
        "dataDocumento": "2022-02-28",
        "numDocumento": "202200000000133",
        "valorDocumento": 15000.0,
        "urlDocumento": "https://www.camara.leg.br/cota-parlamentar/documentos/publ/3034/2022/7335578.pdf",
        "nomeFornecedor": "K.D DA SILVA GOES",
        "cnpjCpfFornecedor": "32756633000110",
        "valorLiquido": 15000.0,
        "valorGlosa": 0.0,
        "numRessarcimento": "",
        "codLote": 1830764,
        "parcela": 0
    },
    {
        "ano": 2022,
        "mes": 3,
        "tipoDespesa": "DIVULGAÇÃO DA ATIVIDADE PARLAMENTAR.",
        "codDocumento": 7352317,
        "tipoDocumento": "Nota Fiscal",
        "codTipoDocumento": 0,
        "dataDocumento": "2022-03-25",
        "numDocumento": "202200000000137",
        "valorDocumento": 15000.0,
        "urlDocumento": "https://www.camara.leg.br/cota-parlamentar/documentos/publ/3034/2022/7352317.pdf",
        "nomeFornecedor": "K.D DA SILVA GOES",
        "cnpjCpfFornecedor": "32756633000110",
        "valorLiquido": 15000.0,
        "valorGlosa": 0.0,
        "numRessarcimento": "",
        "codLote": 1838982,
        "parcela": 0
    },
    {
        "ano": 2022,
        "mes": 2,
        "tipoDespesa": "DIVULGAÇÃO DA ATIVIDADE PARLAMENTAR.",
        "codDocumento": 7335576,
        "tipoDocumento": "Nota Fiscal",
        "codTipoDocumento": 0,
        "dataDocumento": "2022-03-03",
        "numDocumento": "202200000000125",
        "valorDocumento": 2000.0,
        "urlDocumento": "https://www.camara.leg.br/cota-parlamentar/documentos/publ/3034/2022/7335576.pdf",
        "nomeFornecedor": "RAIMUNDO DE DEUS LOIOLA BELAIR",
        "cnpjCpfFornecedor": "23882113000163",
        "valorLiquido": 2000.0,
        "valorGlosa": 0.0,
        "numRessarcimento": "",
        "codLote": 1830763,
        "parcela": 0
    },
    {
        "ano": 2022,
        "mes": 1,
        "tipoDespesa": "TELEFONIA",
        "codDocumento": 0,
        "tipoDocumento": "Nota Fiscal",
        "codTipoDocumento": 0,
        "dataDocumento": "2022-02-26",
        "numDocumento": "7350130",
        "valorDocumento": 116.43,
        "urlDocumento": null,
        "nomeFornecedor": "CELULAR FUNCIONAL",
        "cnpjCpfFornecedor": "00000000000001",
        "valorLiquido": 116.43,
        "valorGlosa": 0.0,
        "numRessarcimento": "0",
        "codLote": 0,
        "parcela": 0
    },
    {
        "ano": 2022,
        "mes": 2,
        "tipoDespesa": "TELEFONIA",
        "codDocumento": 0,
        "tipoDocumento": "Nota Fiscal",
        "codTipoDocumento": 0,
        "dataDocumento": "2022-04-05",
        "numDocumento": "7368074",
        "valorDocumento": 116.43,
        "urlDocumento": null,
        "nomeFornecedor": "CELULAR FUNCIONAL",
        "cnpjCpfFornecedor": "00000000000001",
        "valorLiquido": 116.43,
        "valorGlosa": 0.0,
        "numRessarcimento": "0",
        "codLote": 0,
        "parcela": 0
    },
    {
        "ano": 2022,
        "mes": 3,
        "tipoDespesa": "TELEFONIA",
        "codDocumento": 0,
        "tipoDocumento": "Nota Fiscal",
        "codTipoDocumento": 0,
        "dataDocumento": "2022-08-27",
        "numDocumento": "7373458",
        "valorDocumento": 116.43,
        "urlDocumento": null,
        "nomeFornecedor": "CELULAR FUNCIONAL",
        "cnpjCpfFornecedor": "00000000000001",
        "valorLiquido": 116.43,
        "valorGlosa": 0.0,
        "numRessarcimento": "0",
        "codLote": 0,
        "parcela": 0
    },
    {
        "ano": 2022,
        "mes": 1,
        "tipoDespesa": "TELEFONIA",
        "codDocumento": 7326876,
        "tipoDocumento": "Nota Fiscal",
        "codTipoDocumento": 0,
        "dataDocumento": "2022-01-19",
        "numDocumento": "0002021955",
        "valorDocumento": 474.43,
        "urlDocumento": null,
        "nomeFornecedor": "Claro NXT Telecomunicações S.A",
        "cnpjCpfFornecedor": "66970229001805",
        "valorLiquido": 170.81,
        "valorGlosa": 303.62,
        "numRessarcimento": "",
        "codLote": 1826773,
        "parcela": 0
    },
    {
        "ano": 2022,
        "mes": 2,
        "tipoDespesa": "TELEFONIA",
        "codDocumento": 7339887,
        "tipoDocumento": "Nota Fiscal",
        "codTipoDocumento": 0,
        "dataDocumento": "2022-02-18",
        "numDocumento": "000239090",
        "valorDocumento": 483.65,
        "urlDocumento": null,
        "nomeFornecedor": "Claro NXT Telecomunicações S.A",
        "cnpjCpfFornecedor": "66970229001805",
        "valorLiquido": 170.81,
        "valorGlosa": 312.84,
        "numRessarcimento": "",
        "codLote": 1832780,
        "parcela": 0
    },
    {
        "ano": 2022,
        "mes": 3,
        "tipoDespesa": "TELEFONIA",
        "codDocumento": 7369015,
        "tipoDocumento": "Nota Fiscal",
        "codTipoDocumento": 0,
        "dataDocumento": "2022-03-18",
        "numDocumento": "0002676218",
        "valorDocumento": 508.57,
        "urlDocumento": null,
        "nomeFornecedor": "Claro NXT Telecomunicações S.A",
        "cnpjCpfFornecedor": "66970229001805",
        "valorLiquido": 170.81,
        "valorGlosa": 337.76,
        "numRessarcimento": "",
        "codLote": 1846921,
        "parcela": 0
    },
    {
        "ano": 2022,
        "mes": 3,
        "tipoDespesa": "TELEFONIA",
        "codDocumento": 7357407,
        "tipoDocumento": "Nota Fiscal",
        "codTipoDocumento": 0,
        "dataDocumento": "2022-04-01",
        "numDocumento": "00001120040982",
        "valorDocumento": 249.99,
        "urlDocumento": null,
        "nomeFornecedor": "Telefonica Brasil S.A.",
        "cnpjCpfFornecedor": "02558157000162",
        "valorLiquido": 249.99,
        "valorGlosa": 0.0,
        "numRessarcimento": "",
        "codLote": 1841158,
        "parcela": 0
    },
    {
        "ano": 2022,
        "mes": 2,
        "tipoDespesa": "TELEFONIA",
        "codDocumento": 7340212,
        "tipoDocumento": "Nota Fiscal",
        "codTipoDocumento": 0,
        "dataDocumento": "2022-03-01",
        "numDocumento": "00001120040982",
        "valorDocumento": 249.99,
        "urlDocumento": null,
        "nomeFornecedor": "Telefônica Brasil S.A. VIVO",
        "cnpjCpfFornecedor": "02558157000162",
        "valorLiquido": 173.99,
        "valorGlosa": 76.0,
        "numRessarcimento": "",
        "codLote": 1832935,
        "parcela": 0
    },
    {
        "ano": 2022,
        "mes": 1,
        "tipoDespesa": "TELEFONIA",
        "codDocumento": 7326858,
        "tipoDocumento": "Nota Fiscal",
        "codTipoDocumento": 0,
        "dataDocumento": "2022-02-01",
        "numDocumento": "1334208",
        "valorDocumento": 249.99,
        "urlDocumento": null,
        "nomeFornecedor": "Telefônica Brasil S.A. VIVO",
        "cnpjCpfFornecedor": "02558157000162",
        "valorLiquido": 249.99,
        "valorGlosa": 0.0,
        "numRessarcimento": "",
        "codLote": 1826763,
        "parcela": 0
    },
    {
        "ano": 2022,
        "mes": 1,
        "tipoDespesa": "LOCAÇÃO OU FRETAMENTO DE VEÍCULOS AUTOMOTORES",
        "codDocumento": 7322287,
        "tipoDocumento": "Recibos/Outros",
        "codTipoDocumento": 1,
        "dataDocumento": "2022-01-01",
        "numDocumento": "001",
        "valorDocumento": 8100.0,
        "urlDocumento": "https://www.camara.leg.br/cota-parlamentar/documentos/publ/3034/2022/7322287.pdf",
        "nomeFornecedor": "A & A AGRA LTDA",
        "cnpjCpfFornecedor": "12064991000155",
        "valorLiquido": 8100.0,
        "valorGlosa": 0.0,
        "numRessarcimento": "",
        "codLote": 1824514,
        "parcela": 0
    },
    {
        "ano": 2022,
        "mes": 2,
        "tipoDespesa": "LOCAÇÃO OU FRETAMENTO DE VEÍCULOS AUTOMOTORES",
        "codDocumento": 7337937,
        "tipoDocumento": "Recibos/Outros",
        "codTipoDocumento": 1,
        "dataDocumento": "2022-02-01",
        "numDocumento": "003/2022",
        "valorDocumento": 8100.0,
        "urlDocumento": "https://www.camara.leg.br/cota-parlamentar/documentos/publ/3034/2022/7337937.pdf",
        "nomeFornecedor": "A & A AGRA LTDA",
        "cnpjCpfFornecedor": "12064991000155",
        "valorLiquido": 8100.0,
        "valorGlosa": 0.0,
        "numRessarcimento": "",
        "codLote": 1832021,
        "parcela": 0
    },
    {
        "ano": 2022,
        "mes": 3,
        "tipoDespesa": "LOCAÇÃO OU FRETAMENTO DE VEÍCULOS AUTOMOTORES",
        "codDocumento": 7355608,
        "tipoDocumento": "Recibos/Outros",
        "codTipoDocumento": 1,
        "dataDocumento": "2022-03-01",
        "numDocumento": "004/2022",
        "valorDocumento": 8100.0,
        "urlDocumento": "https://www.camara.leg.br/cota-parlamentar/documentos/publ/3034/2022/7355608.pdf",
        "nomeFornecedor": "A & A AGRA LTDA",
        "cnpjCpfFornecedor": "12064991000155",
        "valorLiquido": 8100.0,
        "valorGlosa": 0.0,
        "numRessarcimento": "",
        "codLote": 1840355,
        "parcela": 0
    },
    {
        "ano": 2022,
        "mes": 3,
        "tipoDespesa": "LOCAÇÃO OU FRETAMENTO DE VEÍCULOS AUTOMOTORES",
        "codDocumento": 7352489,
        "tipoDocumento": "Recibos/Outros",
        "codTipoDocumento": 1,
        "dataDocumento": "2022-03-01",
        "numDocumento": "0042022",
        "valorDocumento": 3150.0,
        "urlDocumento": "https://www.camara.leg.br/cota-parlamentar/documentos/publ/3034/2022/7352489.pdf",
        "nomeFornecedor": "A & A AGRA LTDA",
        "cnpjCpfFornecedor": "12064991000155",
        "valorLiquido": 3150.0,
        "valorGlosa": 0.0,
        "numRessarcimento": "",
        "codLote": 1839008,
        "parcela": 0
    },
    {
        "ano": 2022,
        "mes": 2,
        "tipoDespesa": "LOCAÇÃO OU FRETAMENTO DE EMBARCAÇÕES",
        "codDocumento": 7338348,
        "tipoDocumento": "Nota Fiscal",
        "codTipoDocumento": 0,
        "dataDocumento": "2022-02-28",
        "numDocumento": "3149",
        "valorDocumento": 2500.0,
        "urlDocumento": "https://www.camara.leg.br/cota-parlamentar/documentos/publ/3034/2022/7338348.pdf",
        "nomeFornecedor": "WELLINGTON BRAGA COSTA",
        "cnpjCpfFornecedor": "72713011272",
        "valorLiquido": 2500.0,
        "valorGlosa": 0.0,
        "numRessarcimento": "",
        "codLote": 1832109,
        "parcela": 0
    },
    {
        "ano": 2022,
        "mes": 2,
        "tipoDespesa": "SERVIÇO DE TÁXI, PEDÁGIO E ESTACIONAMENTO",
        "codDocumento": 7333557,
        "tipoDocumento": "Recibos/Outros",
        "codTipoDocumento": 1,
        "dataDocumento": "2022-02-03",
        "numDocumento": "s/n",
        "valorDocumento": 52.0,
        "urlDocumento": "https://www.camara.leg.br/cota-parlamentar/documentos/publ/3034/2022/7333557.pdf",
        "nomeFornecedor": "COOPERATIVA DO PONTO DE TAXI 202 NORTE - COOPERNORTE",
        "cnpjCpfFornecedor": "08046163000117",
        "valorLiquido": 52.0,
        "valorGlosa": 0.0,
        "numRessarcimento": "",
        "codLote": 1829852,
        "parcela": 0
    },
    {
        "ano": 2022,
        "mes": 2,
        "tipoDespesa": "SERVIÇO DE TÁXI, PEDÁGIO E ESTACIONAMENTO",
        "codDocumento": 7333580,
        "tipoDocumento": "Recibos/Outros",
        "codTipoDocumento": 1,
        "dataDocumento": "2022-02-23",
        "numDocumento": "S/N",
        "valorDocumento": 20.0,
        "urlDocumento": "https://www.camara.leg.br/cota-parlamentar/documentos/publ/3034/2022/7333580.pdf",
        "nomeFornecedor": "COOPERATIVA DO PONTO DE TAXI 202 NORTE - COOPERNORTE",
        "cnpjCpfFornecedor": "08046163000117",
        "valorLiquido": 20.0,
        "valorGlosa": 0.0,
        "numRessarcimento": "",
        "codLote": 1829857,
        "parcela": 0
    },
    {
        "ano": 2022,
        "mes": 2,
        "tipoDespesa": "SERVIÇO DE TÁXI, PEDÁGIO E ESTACIONAMENTO",
        "codDocumento": 7327633,
        "tipoDocumento": "Recibos/Outros",
        "codTipoDocumento": 1,
        "dataDocumento": "2022-02-08",
        "numDocumento": "s/n",
        "valorDocumento": 65.0,
        "urlDocumento": "https://www.camara.leg.br/cota-parlamentar/documentos/publ/3034/2022/7327633.pdf",
        "nomeFornecedor": "COOPERTAXI 202 NORTE",
        "cnpjCpfFornecedor": "08046163000117",
        "valorLiquido": 65.0,
        "valorGlosa": 0.0,
        "numRessarcimento": "",
        "codLote": 1827119,
        "parcela": 0
    },
    {
        "ano": 2022,
        "mes": 2,
        "tipoDespesa": "SERVIÇO DE TÁXI, PEDÁGIO E ESTACIONAMENTO",
        "codDocumento": 7330605,
        "tipoDocumento": "Recibos/Outros",
        "codTipoDocumento": 1,
        "dataDocumento": "2022-02-08",
        "numDocumento": "S/N",
        "valorDocumento": 65.0,
        "urlDocumento": "https://www.camara.leg.br/cota-parlamentar/documentos/publ/3034/2022/7330605.pdf",
        "nomeFornecedor": "COOPERTAXI 202 NORTE",
        "cnpjCpfFornecedor": "08046163000117",
        "valorLiquido": 65.0,
        "valorGlosa": 0.0,
        "numRessarcimento": "",
        "codLote": 1828491,
        "parcela": 0
    },
    {
        "ano": 2022,
        "mes": 2,
        "tipoDespesa": "SERVIÇO DE TÁXI, PEDÁGIO E ESTACIONAMENTO",
        "codDocumento": 7330580,
        "tipoDocumento": "Recibos/Outros",
        "codTipoDocumento": 1,
        "dataDocumento": "2022-02-10",
        "numDocumento": "S/N",
        "valorDocumento": 60.0,
        "urlDocumento": "https://www.camara.leg.br/cota-parlamentar/documentos/publ/3034/2022/7330580.pdf",
        "nomeFornecedor": "COOPERTAXI 202 NORTE",
        "cnpjCpfFornecedor": "08046163000117",
        "valorLiquido": 60.0,
        "valorGlosa": 0.0,
        "numRessarcimento": "",
        "codLote": 1828478,
        "parcela": 0
    },
    {
        "ano": 2022,
        "mes": 3,
        "tipoDespesa": "SERVIÇO DE TÁXI, PEDÁGIO E ESTACIONAMENTO",
        "codDocumento": 7349201,
        "tipoDocumento": "Recibos/Outros",
        "codTipoDocumento": 1,
        "dataDocumento": "2022-03-22",
        "numDocumento": "s/n",
        "valorDocumento": 60.0,
        "urlDocumento": "https://www.camara.leg.br/cota-parlamentar/documentos/publ/3034/2022/7349201.pdf",
        "nomeFornecedor": "COOPERTAXI 202 NORTE",
        "cnpjCpfFornecedor": "08046163000117",
        "valorLiquido": 60.0,
        "valorGlosa": 0.0,
        "numRessarcimento": "",
        "codLote": 1837054,
        "parcela": 0
    },
    {
        "ano": 2022,
        "mes": 4,
        "tipoDespesa": "SERVIÇO DE TÁXI, PEDÁGIO E ESTACIONAMENTO",
        "codDocumento": 7368790,
        "tipoDocumento": "Recibos/Outros",
        "codTipoDocumento": 1,
        "dataDocumento": "2022-04-19",
        "numDocumento": "S/N",
        "valorDocumento": 20.0,
        "urlDocumento": "https://www.camara.leg.br/cota-parlamentar/documentos/publ/3034/2022/7368790.pdf",
        "nomeFornecedor": "COOPERTAXI 202 NORTE",
        "cnpjCpfFornecedor": "08046163000117",
        "valorLiquido": 20.0,
        "valorGlosa": 0.0,
        "numRessarcimento": "",
        "codLote": 1846832,
        "parcela": 0
    },
    {
        "ano": 2022,
        "mes": 4,
        "tipoDespesa": "SERVIÇO DE TÁXI, PEDÁGIO E ESTACIONAMENTO",
        "codDocumento": 7368715,
        "tipoDocumento": "Recibos/Outros",
        "codTipoDocumento": 1,
        "dataDocumento": "2022-04-20",
        "numDocumento": "S/N",
        "valorDocumento": 72.0,
        "urlDocumento": "https://www.camara.leg.br/cota-parlamentar/documentos/publ/3034/2022/7368715.pdf",
        "nomeFornecedor": "COOPERTAXI 202 NORTE",
        "cnpjCpfFornecedor": "08046163000117",
        "valorLiquido": 72.0,
        "valorGlosa": 0.0,
        "numRessarcimento": "",
        "codLote": 1846790,
        "parcela": 0
    },
    {
        "ano": 2022,
        "mes": 4,
        "tipoDespesa": "SERVIÇO DE TÁXI, PEDÁGIO E ESTACIONAMENTO",
        "codDocumento": 7368796,
        "tipoDocumento": "Recibos/Outros",
        "codTipoDocumento": 1,
        "dataDocumento": "2022-04-26",
        "numDocumento": "S/N",
        "valorDocumento": 20.0,
        "urlDocumento": "https://www.camara.leg.br/cota-parlamentar/documentos/publ/3034/2022/7368796.pdf",
        "nomeFornecedor": "COOPERTAXI 202 NORTE",
        "cnpjCpfFornecedor": "08046163000117",
        "valorLiquido": 20.0,
        "valorGlosa": 0.0,
        "numRessarcimento": "",
        "codLote": 1846912,
        "parcela": 0
    },
    {
        "ano": 2022,
        "mes": 5,
        "tipoDespesa": "SERVIÇO DE TÁXI, PEDÁGIO E ESTACIONAMENTO",
        "codDocumento": 7375026,
        "tipoDocumento": "Recibos/Outros",
        "codTipoDocumento": 1,
        "dataDocumento": "2022-05-03",
        "numDocumento": "S/N",
        "valorDocumento": 63.0,
        "urlDocumento": "https://www.camara.leg.br/cota-parlamentar/documentos/publ/3034/2022/7375026.pdf",
        "nomeFornecedor": "COOPERTAXI 202 NORTE",
        "cnpjCpfFornecedor": "08046163000117",
        "valorLiquido": 63.0,
        "valorGlosa": 0.0,
        "numRessarcimento": "",
        "codLote": 1850667,
        "parcela": 0
    },
    {
        "ano": 2022,
        "mes": 2,
        "tipoDespesa": "SERVIÇO DE TÁXI, PEDÁGIO E ESTACIONAMENTO",
        "codDocumento": 7330372,
        "tipoDocumento": "Recibos/Outros",
        "codTipoDocumento": 1,
        "dataDocumento": "2022-02-14",
        "numDocumento": "S/N",
        "valorDocumento": 63.29,
        "urlDocumento": "https://www.camara.leg.br/cota-parlamentar/documentos/publ/3034/2022/7330372.pdf",
        "nomeFornecedor": "SAFERTAXI",
        "cnpjCpfFornecedor": "12305217000199",
        "valorLiquido": 63.29,
        "valorGlosa": 0.0,
        "numRessarcimento": "",
        "codLote": 1828373,
        "parcela": 0
    },
    {
        "ano": 2022,
        "mes": 2,
        "tipoDespesa": "SERVIÇO DE TÁXI, PEDÁGIO E ESTACIONAMENTO",
        "codDocumento": 7333571,
        "tipoDocumento": "Recibos/Outros",
        "codTipoDocumento": 1,
        "dataDocumento": "2022-02-22",
        "numDocumento": "S/N",
        "valorDocumento": 62.34,
        "urlDocumento": "https://www.camara.leg.br/cota-parlamentar/documentos/publ/3034/2022/7333571.pdf",
        "nomeFornecedor": "SAFERTAXI",
        "cnpjCpfFornecedor": "12305217000199",
        "valorLiquido": 62.34,
        "valorGlosa": 0.0,
        "numRessarcimento": "",
        "codLote": 1829855,
        "parcela": 0
    },
    {
        "ano": 2022,
        "mes": 4,
        "tipoDespesa": "SERVIÇO DE TÁXI, PEDÁGIO E ESTACIONAMENTO",
        "codDocumento": 7370034,
        "tipoDocumento": "Recibos/Outros",
        "codTipoDocumento": 1,
        "dataDocumento": "2022-04-25",
        "numDocumento": "S/N",
        "valorDocumento": 63.49,
        "urlDocumento": "https://www.camara.leg.br/cota-parlamentar/documentos/publ/3034/2022/7370034.pdf",
        "nomeFornecedor": "SAFERTAXI",
        "cnpjCpfFornecedor": "12305217000199",
        "valorLiquido": 63.49,
        "valorGlosa": 0.0,
        "numRessarcimento": "",
        "codLote": 1847364,
        "parcela": 0
    },
    {
        "ano": 2022,
        "mes": 1,
        "tipoDespesa": "PASSAGEM AÉREA - SIGEPA",
        "codDocumento": 69550,
        "tipoDocumento": "Nota Fiscal",
        "codTipoDocumento": 0,
        "dataDocumento": "2022-01-06",
        "numDocumento": "1272167195168",
        "valorDocumento": 464.91,
        "urlDocumento": null,
        "nomeFornecedor": "GOL",
        "cnpjCpfFornecedor": "",
        "valorLiquido": 464.91,
        "valorGlosa": 0.0,
        "numRessarcimento": "0",
        "codLote": 0,
        "parcela": 0
    },
    {
        "ano": 2022,
        "mes": 1,
        "tipoDespesa": "PASSAGEM AÉREA - SIGEPA",
        "codDocumento": 69557,
        "tipoDocumento": "Nota Fiscal",
        "codTipoDocumento": 0,
        "dataDocumento": "2022-01-06",
        "numDocumento": "1272167198170",
        "valorDocumento": 464.91,
        "urlDocumento": null,
        "nomeFornecedor": "GOL",
        "cnpjCpfFornecedor": "",
        "valorLiquido": 464.91,
        "valorGlosa": 0.0,
        "numRessarcimento": "0",
        "codLote": 0,
        "parcela": 0
    },
    {
        "ano": 2022,
        "mes": 2,
        "tipoDespesa": "PASSAGEM AÉREA - SIGEPA",
        "codDocumento": 74513,
        "tipoDocumento": "Nota Fiscal",
        "codTipoDocumento": 0,
        "dataDocumento": "2022-02-16",
        "numDocumento": "1272169649000",
        "valorDocumento": 45.0,
        "urlDocumento": null,
        "nomeFornecedor": "GOL",
        "cnpjCpfFornecedor": "",
        "valorLiquido": 45.0,
        "valorGlosa": 0.0,
        "numRessarcimento": "0",
        "codLote": 0,
        "parcela": 0
    },
    {
        "ano": 2022,
        "mes": 2,
        "tipoDespesa": "PASSAGEM AÉREA - SIGEPA",
        "codDocumento": 74513,
        "tipoDocumento": "Nota Fiscal",
        "codTipoDocumento": 0,
        "dataDocumento": "2022-02-16",
        "numDocumento": "1272169649000",
        "valorDocumento": 415.83,
        "urlDocumento": null,
        "nomeFornecedor": "GOL",
        "cnpjCpfFornecedor": "",
        "valorLiquido": 415.83,
        "valorGlosa": 0.0,
        "numRessarcimento": "0",
        "codLote": 0,
        "parcela": 0
    },
    {
        "ano": 2022,
        "mes": 2,
        "tipoDespesa": "PASSAGEM AÉREA - SIGEPA",
        "codDocumento": 74525,
        "tipoDocumento": "Nota Fiscal",
        "codTipoDocumento": 0,
        "dataDocumento": "2022-02-16",
        "numDocumento": "1272169652022",
        "valorDocumento": 45.0,
        "urlDocumento": null,
        "nomeFornecedor": "GOL",
        "cnpjCpfFornecedor": "",
        "valorLiquido": 45.0,
        "valorGlosa": 0.0,
        "numRessarcimento": "0",
        "codLote": 0,
        "parcela": 0
    },
    {
        "ano": 2022,
        "mes": 2,
        "tipoDespesa": "PASSAGEM AÉREA - SIGEPA",
        "codDocumento": 74525,
        "tipoDocumento": "Nota Fiscal",
        "codTipoDocumento": 0,
        "dataDocumento": "2022-02-16",
        "numDocumento": "1272169652022",
        "valorDocumento": 421.83,
        "urlDocumento": null,
        "nomeFornecedor": "GOL",
        "cnpjCpfFornecedor": "",
        "valorLiquido": 421.83,
        "valorGlosa": 0.0,
        "numRessarcimento": "0",
        "codLote": 0,
        "parcela": 0
    },
    {
        "ano": 2022,
        "mes": 2,
        "tipoDespesa": "PASSAGEM AÉREA - SIGEPA",
        "codDocumento": 74610,
        "tipoDocumento": "Nota Fiscal",
        "codTipoDocumento": 0,
        "dataDocumento": "2022-02-16",
        "numDocumento": "1272169674024",
        "valorDocumento": 1387.36,
        "urlDocumento": null,
        "nomeFornecedor": "GOL",
        "cnpjCpfFornecedor": "",
        "valorLiquido": 1387.36,
        "valorGlosa": 0.0,
        "numRessarcimento": "0",
        "codLote": 0,
        "parcela": 0
    },
    {
        "ano": 2022,
        "mes": 2,
        "tipoDespesa": "PASSAGEM AÉREA - SIGEPA",
        "codDocumento": 75076,
        "tipoDocumento": "Nota Fiscal",
        "codTipoDocumento": 0,
        "dataDocumento": "2022-02-22",
        "numDocumento": "1272169997916",
        "valorDocumento": 1713.63,
        "urlDocumento": null,
        "nomeFornecedor": "GOL",
        "cnpjCpfFornecedor": "",
        "valorLiquido": 1713.63,
        "valorGlosa": 0.0,
        "numRessarcimento": "0",
        "codLote": 0,
        "parcela": 0
    },
    {
        "ano": 2022,
        "mes": 1,
        "tipoDespesa": "PASSAGEM AÉREA - SIGEPA",
        "codDocumento": 69549,
        "tipoDocumento": "Nota Fiscal",
        "codTipoDocumento": 0,
        "dataDocumento": "2022-01-06",
        "numDocumento": "9572166576383",
        "valorDocumento": 75.0,
        "urlDocumento": null,
        "nomeFornecedor": "TAM",
        "cnpjCpfFornecedor": "",
        "valorLiquido": 75.0,
        "valorGlosa": 0.0,
        "numRessarcimento": "0",
        "codLote": 0,
        "parcela": 0
    },
    {
        "ano": 2022,
        "mes": 1,
        "tipoDespesa": "PASSAGEM AÉREA - SIGEPA",
        "codDocumento": 69549,
        "tipoDocumento": "Nota Fiscal",
        "codTipoDocumento": 0,
        "dataDocumento": "2022-01-06",
        "numDocumento": "9572166576383",
        "valorDocumento": 463.89,
        "urlDocumento": null,
        "nomeFornecedor": "TAM",
        "cnpjCpfFornecedor": "",
        "valorLiquido": 463.89,
        "valorGlosa": 0.0,
        "numRessarcimento": "0",
        "codLote": 0,
        "parcela": 0
    },
    {
        "ano": 2022,
        "mes": 1,
        "tipoDespesa": "PASSAGEM AÉREA - SIGEPA",
        "codDocumento": 69551,
        "tipoDocumento": "Nota Fiscal",
        "codTipoDocumento": 0,
        "dataDocumento": "2022-01-06",
        "numDocumento": "9572166578205",
        "valorDocumento": 75.0,
        "urlDocumento": null,
        "nomeFornecedor": "TAM",
        "cnpjCpfFornecedor": "",
        "valorLiquido": 75.0,
        "valorGlosa": 0.0,
        "numRessarcimento": "0",
        "codLote": 0,
        "parcela": 0
    },
    {
        "ano": 2022,
        "mes": 1,
        "tipoDespesa": "PASSAGEM AÉREA - SIGEPA",
        "codDocumento": 69551,
        "tipoDocumento": "Nota Fiscal",
        "codTipoDocumento": 0,
        "dataDocumento": "2022-01-06",
        "numDocumento": "9572166578205",
        "valorDocumento": 461.95,
        "urlDocumento": null,
        "nomeFornecedor": "TAM",
        "cnpjCpfFornecedor": "",
        "valorLiquido": 461.95,
        "valorGlosa": 0.0,
        "numRessarcimento": "0",
        "codLote": 0,
        "parcela": 0
    },
    {
        "ano": 2022,
        "mes": 1,
        "tipoDespesa": "PASSAGEM AÉREA - SIGEPA",
        "codDocumento": 69555,
        "tipoDocumento": "Nota Fiscal",
        "codTipoDocumento": 0,
        "dataDocumento": "2022-01-06",
        "numDocumento": "9572166579143",
        "valorDocumento": 55.0,
        "urlDocumento": null,
        "nomeFornecedor": "TAM",
        "cnpjCpfFornecedor": "",
        "valorLiquido": 55.0,
        "valorGlosa": 0.0,
        "numRessarcimento": "0",
        "codLote": 0,
        "parcela": 0
    },
    {
        "ano": 2022,
        "mes": 1,
        "tipoDespesa": "PASSAGEM AÉREA - SIGEPA",
        "codDocumento": 69555,
        "tipoDocumento": "Nota Fiscal",
        "codTipoDocumento": 0,
        "dataDocumento": "2022-01-06",
        "numDocumento": "9572166579143",
        "valorDocumento": 464.91,
        "urlDocumento": null,
        "nomeFornecedor": "TAM",
        "cnpjCpfFornecedor": "",
        "valorLiquido": 464.91,
        "valorGlosa": 0.0,
        "numRessarcimento": "0",
        "codLote": 0,
        "parcela": 0
    },
    {
        "ano": 2022,
        "mes": 1,
        "tipoDespesa": "PASSAGEM AÉREA - SIGEPA",
        "codDocumento": 69556,
        "tipoDocumento": "Nota Fiscal",
        "codTipoDocumento": 0,
        "dataDocumento": "2022-01-06",
        "numDocumento": "9572166579677",
        "valorDocumento": 55.0,
        "urlDocumento": null,
        "nomeFornecedor": "TAM",
        "cnpjCpfFornecedor": "",
        "valorLiquido": 55.0,
        "valorGlosa": 0.0,
        "numRessarcimento": "0",
        "codLote": 0,
        "parcela": 0
    },
    {
        "ano": 2022,
        "mes": 1,
        "tipoDespesa": "PASSAGEM AÉREA - SIGEPA",
        "codDocumento": 69556,
        "tipoDocumento": "Nota Fiscal",
        "codTipoDocumento": 0,
        "dataDocumento": "2022-01-06",
        "numDocumento": "9572166579677",
        "valorDocumento": 461.95,
        "urlDocumento": null,
        "nomeFornecedor": "TAM",
        "cnpjCpfFornecedor": "",
        "valorLiquido": 461.95,
        "valorGlosa": 0.0,
        "numRessarcimento": "0",
        "codLote": 0,
        "parcela": 0
    },
    {
        "ano": 2022,
        "mes": 2,
        "tipoDespesa": "PASSAGEM AÉREA - SIGEPA",
        "codDocumento": 72611,
        "tipoDocumento": "Nota Fiscal",
        "codTipoDocumento": 0,
        "dataDocumento": "2022-02-02",
        "numDocumento": "9572169332442",
        "valorDocumento": 1935.43,
        "urlDocumento": null,
        "nomeFornecedor": "TAM",
        "cnpjCpfFornecedor": "",
        "valorLiquido": 1935.43,
        "valorGlosa": 0.0,
        "numRessarcimento": "0",
        "codLote": 0,
        "parcela": 0
    },
    {
        "ano": 2022,
        "mes": 2,
        "tipoDespesa": "PASSAGEM AÉREA - SIGEPA",
        "codDocumento": 73659,
        "tipoDocumento": "Nota Fiscal",
        "codTipoDocumento": 0,
        "dataDocumento": "2022-02-09",
        "numDocumento": "9572169914992",
        "valorDocumento": 1946.89,
        "urlDocumento": null,
        "nomeFornecedor": "TAM",
        "cnpjCpfFornecedor": "",
        "valorLiquido": 1946.89,
        "valorGlosa": 0.0,
        "numRessarcimento": "0",
        "codLote": 0,
        "parcela": 0
    },
    {
        "ano": 2022,
        "mes": 2,
        "tipoDespesa": "PASSAGEM AÉREA - SIGEPA",
        "codDocumento": 74294,
        "tipoDocumento": "Nota Fiscal",
        "codTipoDocumento": 0,
        "dataDocumento": "2022-02-15",
        "numDocumento": "9572170367579",
        "valorDocumento": 220.26,
        "urlDocumento": null,
        "nomeFornecedor": "TAM",
        "cnpjCpfFornecedor": "",
        "valorLiquido": 220.26,
        "valorGlosa": 0.0,
        "numRessarcimento": "0",
        "codLote": 0,
        "parcela": 0
    },
    {
        "ano": 2022,
        "mes": 2,
        "tipoDespesa": "PASSAGEM AÉREA - SIGEPA",
        "codDocumento": 74509,
        "tipoDocumento": "Nota Fiscal",
        "codTipoDocumento": 0,
        "dataDocumento": "2022-02-16",
        "numDocumento": "9572170491974",
        "valorDocumento": 455.03,
        "urlDocumento": null,
        "nomeFornecedor": "TAM",
        "cnpjCpfFornecedor": "",
        "valorLiquido": 455.03,
        "valorGlosa": 0.0,
        "numRessarcimento": "0",
        "codLote": 0,
        "parcela": 0
    },
    {
        "ano": 2022,
        "mes": 2,
        "tipoDespesa": "PASSAGEM AÉREA - SIGEPA",
        "codDocumento": 74512,
        "tipoDocumento": "Nota Fiscal",
        "codTipoDocumento": 0,
        "dataDocumento": "2022-02-16",
        "numDocumento": "9572170492547",
        "valorDocumento": 455.03,
        "urlDocumento": null,
        "nomeFornecedor": "TAM",
        "cnpjCpfFornecedor": "",
        "valorLiquido": 455.03,
        "valorGlosa": 0.0,
        "numRessarcimento": "0",
        "codLote": 0,
        "parcela": 0
    },
    {
        "ano": 2022,
        "mes": 2,
        "tipoDespesa": "PASSAGEM AÉREA - SIGEPA",
        "codDocumento": 74515,
        "tipoDocumento": "Nota Fiscal",
        "codTipoDocumento": 0,
        "dataDocumento": "2022-02-16",
        "numDocumento": "9572170493779",
        "valorDocumento": 433.69,
        "urlDocumento": null,
        "nomeFornecedor": "TAM",
        "cnpjCpfFornecedor": "",
        "valorLiquido": 433.69,
        "valorGlosa": 0.0,
        "numRessarcimento": "0",
        "codLote": 0,
        "parcela": 0
    },
    {
        "ano": 2022,
        "mes": 2,
        "tipoDespesa": "PASSAGEM AÉREA - SIGEPA",
        "codDocumento": 74516,
        "tipoDocumento": "Nota Fiscal",
        "codTipoDocumento": 0,
        "dataDocumento": "2022-02-16",
        "numDocumento": "9572170494635",
        "valorDocumento": 461.03,
        "urlDocumento": null,
        "nomeFornecedor": "TAM",
        "cnpjCpfFornecedor": "",
        "valorLiquido": 461.03,
        "valorGlosa": 0.0,
        "numRessarcimento": "0",
        "codLote": 0,
        "parcela": 0
    },
    {
        "ano": 2022,
        "mes": 2,
        "tipoDespesa": "PASSAGEM AÉREA - SIGEPA",
        "codDocumento": 74518,
        "tipoDocumento": "Nota Fiscal",
        "codTipoDocumento": 0,
        "dataDocumento": "2022-02-16",
        "numDocumento": "9572170494696",
        "valorDocumento": 439.69,
        "urlDocumento": null,
        "nomeFornecedor": "TAM",
        "cnpjCpfFornecedor": "",
        "valorLiquido": 439.69,
        "valorGlosa": 0.0,
        "numRessarcimento": "0",
        "codLote": 0,
        "parcela": 0
    },
    {
        "ano": 2022,
        "mes": 2,
        "tipoDespesa": "PASSAGEM AÉREA - SIGEPA",
        "codDocumento": 74524,
        "tipoDocumento": "Nota Fiscal",
        "codTipoDocumento": 0,
        "dataDocumento": "2022-02-16",
        "numDocumento": "9572170496361",
        "valorDocumento": 439.69,
        "urlDocumento": null,
        "nomeFornecedor": "TAM",
        "cnpjCpfFornecedor": "",
        "valorLiquido": 439.69,
        "valorGlosa": 0.0,
        "numRessarcimento": "0",
        "codLote": 0,
        "parcela": 0
    },
    {
        "ano": 2022,
        "mes": 2,
        "tipoDespesa": "PASSAGEM AÉREA - SIGEPA",
        "codDocumento": 75601,
        "tipoDocumento": "Nota Fiscal",
        "codTipoDocumento": 0,
        "dataDocumento": "2022-02-25",
        "numDocumento": "9572171260635",
        "valorDocumento": 69.0,
        "urlDocumento": null,
        "nomeFornecedor": "TAM",
        "cnpjCpfFornecedor": "",
        "valorLiquido": 69.0,
        "valorGlosa": 0.0,
        "numRessarcimento": "0",
        "codLote": 0,
        "parcela": 0
    },
    {
        "ano": 2022,
        "mes": 2,
        "tipoDespesa": "PASSAGEM AÉREA - SIGEPA",
        "codDocumento": 75601,
        "tipoDocumento": "Nota Fiscal",
        "codTipoDocumento": 0,
        "dataDocumento": "2022-02-25",
        "numDocumento": "9572171260635",
        "valorDocumento": 795.5,
        "urlDocumento": null,
        "nomeFornecedor": "TAM",
        "cnpjCpfFornecedor": "",
        "valorLiquido": 795.5,
        "valorGlosa": 0.0,
        "numRessarcimento": "0",
        "codLote": 0,
        "parcela": 0
    },
    {
        "ano": 2022,
        "mes": 3,
        "tipoDespesa": "PASSAGEM AÉREA - SIGEPA",
        "codDocumento": 75831,
        "tipoDocumento": "Nota Fiscal",
        "codTipoDocumento": 0,
        "dataDocumento": "2022-03-02",
        "numDocumento": "9572171621650",
        "valorDocumento": 55.0,
        "urlDocumento": null,
        "nomeFornecedor": "TAM",
        "cnpjCpfFornecedor": "",
        "valorLiquido": 55.0,
        "valorGlosa": 0.0,
        "numRessarcimento": "0",
        "codLote": 0,
        "parcela": 0
    },
    {
        "ano": 2022,
        "mes": 3,
        "tipoDespesa": "PASSAGEM AÉREA - SIGEPA",
        "codDocumento": 75831,
        "tipoDocumento": "Nota Fiscal",
        "codTipoDocumento": 0,
        "dataDocumento": "2022-03-02",
        "numDocumento": "9572171621650",
        "valorDocumento": 1948.83,
        "urlDocumento": null,
        "nomeFornecedor": "TAM",
        "cnpjCpfFornecedor": "",
        "valorLiquido": 1948.83,
        "valorGlosa": 0.0,
        "numRessarcimento": "0",
        "codLote": 0,
        "parcela": 0
    },
    {
        "ano": 2022,
        "mes": 3,
        "tipoDespesa": "PASSAGEM AÉREA - SIGEPA",
        "codDocumento": 76955,
        "tipoDocumento": "Nota Fiscal",
        "codTipoDocumento": 0,
        "dataDocumento": "2022-03-09",
        "numDocumento": "9572172265529",
        "valorDocumento": 59.0,
        "urlDocumento": null,
        "nomeFornecedor": "TAM",
        "cnpjCpfFornecedor": "",
        "valorLiquido": 59.0,
        "valorGlosa": 0.0,
        "numRessarcimento": "0",
        "codLote": 0,
        "parcela": 0
    },
    {
        "ano": 2022,
        "mes": 3,
        "tipoDespesa": "PASSAGEM AÉREA - SIGEPA",
        "codDocumento": 76955,
        "tipoDocumento": "Nota Fiscal",
        "codTipoDocumento": 0,
        "dataDocumento": "2022-03-09",
        "numDocumento": "9572172265529",
        "valorDocumento": 2167.36,
        "urlDocumento": null,
        "nomeFornecedor": "TAM",
        "cnpjCpfFornecedor": "",
        "valorLiquido": 2167.36,
        "valorGlosa": 0.0,
        "numRessarcimento": "0",
        "codLote": 0,
        "parcela": 0
    },
    {
        "ano": 2022,
        "mes": 3,
        "tipoDespesa": "PASSAGEM AÉREA - SIGEPA",
        "codDocumento": 79789,
        "tipoDocumento": "Nota Fiscal",
        "codTipoDocumento": 0,
        "dataDocumento": "2022-03-30",
        "numDocumento": "9572173855255",
        "valorDocumento": 1372.33,
        "urlDocumento": null,
        "nomeFornecedor": "TAM",
        "cnpjCpfFornecedor": "",
        "valorLiquido": 1372.33,
        "valorGlosa": 0.0,
        "numRessarcimento": "0",
        "codLote": 0,
        "parcela": 0
    },
    {
        "ano": 2022,
        "mes": 2,
        "tipoDespesa": "PASSAGEM AÉREA - RPA",
        "codDocumento": 1763280,
        "tipoDocumento": "Nota Fiscal",
        "codTipoDocumento": 0,
        "dataDocumento": "2022-02-21",
        "numDocumento": "Bilhete: 957-2170.921621",
        "valorDocumento": 2138.23,
        "urlDocumento": null,
        "nomeFornecedor": "Cia Aérea - TAM",
        "cnpjCpfFornecedor": "02012862000160",
        "valorLiquido": 2138.23,
        "valorGlosa": 0.0,
        "numRessarcimento": "0",
        "codLote": 0,
        "parcela": 0
    },
    {
        "ano": 2022,
        "mes": 2,
        "tipoDespesa": "PASSAGEM AÉREA - RPA",
        "codDocumento": 1763292,
        "tipoDocumento": "Nota Fiscal",
        "codTipoDocumento": 0,
        "dataDocumento": "2022-02-22",
        "numDocumento": "Bilhete: 957-2170.991423",
        "valorDocumento": 2347.23,
        "urlDocumento": null,
        "nomeFornecedor": "Cia Aérea - TAM",
        "cnpjCpfFornecedor": "02012862000160",
        "valorLiquido": 2347.23,
        "valorGlosa": 0.0,
        "numRessarcimento": "0",
        "codLote": 0,
        "parcela": 0
    }
]