{
    "proposicoes_by_year": {
        "2019": {
            "amount": 87,
            "types": {
                "REQ": 13,
                "EMC": 66,
                "PL": 6,
                "INC": 1,
                "EMP": 1
            }
        },
        "0": {
            "amount": 27,
            "types": {
                "PRL": 5,
                "SBT": 2,
                "EMP": 9,
                "ATACN": 1,
                "EMC": 8,
                "RRL": 2
            }
        },
        "2020": {
            "amount": 15,
            "types": {
                "REQ": 3,
                "PL": 9,
                "DOC": 3
            }
        },
        "2021": {
            "amount": 27,
            "types": {
                "DOC": 5,
                "PEC": 2,
                "REQ": 12,
                "REC": 2,
                "PL": 6
            }
        },
        "2022": {
            "amount": 3,
            "types": {
                "DOC": 1,
                "REQ": 2
            }
        }
    }
}